{"layers": [{"id": "3FBA298D-5E78-4BAF-A8A1-9B4D07F27683", "name": "bg", "rect": {"x": 0, "y": 0, "width": 375, "height": 812}, "_class": "shapeGroup", "color": [0.847, 0.847, 0.847, 1], "label": 0}, {"id": "A19CD3C5-770B-479B-A7CE-CDABD3D03D85", "name": "Status Bar / Black", "rect": {"x": 0, "y": 0, "width": 374.7849419377487, "height": 19.98853023667994}, "_class": "symbolInstance", "color": [0.0, 0.0, 0.0, 0.0], "label": 1}, {"id": "20A01D3C-6DB5-4DAB-855B-3A9BE54D5896", "name": "iP X - Tab Bar - 5 Tabs", "rect": {"x": 133, "y": 795, "width": 110, "height": 4}, "_class": "symbolInstance", "color": [0.0, 0.0, 0.0, 0.0], "label": 1}, {"id": "72033D55-00FF-489A-9EB4-E98B7B90EDAC", "name": "card", "rect": {"x": -4, "y": 226, "width": 383, "height": 439}, "_class": "shapeGroup", "color": [1, 1, 1, 1], "label": 1}, {"id": "6A6CABC0-A1C5-4E58-B3E8-1BA8B3DCE642", "name": "Sign in", "rect": {"x": 16, "y": 124, "width": 193, "height": 71}, "_class": "text", "color": [0.0, 0.0, 0.0, 0.0], "label": 1}, {"id": "E24A75C1-7047-461F-9E66-5661D61ED0EC", "name": "Sign up", "rect": {"x": 262, "y": 124, "width": 215, "height": 71}, "_class": "text", "color": [0.0, 0.0, 0.0, 0.0], "label": 1}, {"id": "CD7B0980-27A4-47CE-A52C-B79BDBA086C7", "name": "Forgot your password", "rect": {"x": 110.5, "y": 570, "width": 155, "height": 36}, "_class": "text", "color": [0.0, 0.0, 0.0, 0.0], "label": 1}, {"id": "795723EC-A020-4DB6-9176-AB486FB0F1B8", "name": "Rectangle", "rect": {"x": 50, "y": 281, "width": 276, "height": 40}, "_class": "shapeGroup", "color": [0.9607843137254902, 0.9607843137254902, 0.9607843137254902, 1], "label": 1}, {"id": "85F6BF13-ADB3-4DD9-A2B5-453F9779FA3E", "name": "Email", "rect": {"x": 50, "y": 252, "width": 37, "height": 18}, "_class": "text", "color": [0.0, 0.0, 0.0, 0.0], "label": 1}, {"id": "36FB7BBB-96FB-4234-A952-5CA3F1479E73", "name": "support@freeslab.com", "rect": {"x": 65, "y": 292, "width": 153, "height": 18}, "_class": "text", "color": [0.0, 0.0, 0.0, 0.0], "label": 1}, {"id": "0490E090-0133-441D-A3B0-802FBD1F2672", "name": "Rectangle Copy", "rect": {"x": 50, "y": 380, "width": 276, "height": 40}, "_class": "shapeGroup", "color": [0.9607843137254902, 0.9607843137254902, 0.9607843137254902, 1], "label": 1}, {"id": "9DA17B4A-CED9-414A-B2D4-A67D3ECE13CB", "name": "Password", "rect": {"x": 50, "y": 351, "width": 66, "height": 18}, "_class": "text", "color": [0.0, 0.0, 0.0, 0.0], "label": 1}, {"id": "03BAB920-3AEF-482B-AED5-28F8006449A1", "name": "Oval", "rect": {"x": 65, "y": 395, "width": 10, "height": 10}, "_class": "shapeGroup", "color": [0.1490196078431373, 0.1490196078431373, 0.1568627450980392, 1], "label": 1}, {"id": "F27197D6-1B2A-41E4-885B-B59D84EDF43A", "name": "Oval Copy", "rect": {"x": 82, "y": 395, "width": 10, "height": 10}, "_class": "shapeGroup", "color": [0.1490196078431373, 0.1490196078431373, 0.1568627450980392, 1], "label": 1}, {"id": "359617AE-0AEE-463E-9AC2-3CF9FF8783E6", "name": "Oval Copy 2", "rect": {"x": 99, "y": 395, "width": 10, "height": 10}, "_class": "shapeGroup", "color": [0.1490196078431373, 0.1490196078431373, 0.1568627450980392, 1], "label": 1}, {"id": "94A8D770-8E13-4B42-BDD1-39166A2C71D3", "name": "Oval Copy 3", "rect": {"x": 116, "y": 395, "width": 10, "height": 10}, "_class": "shapeGroup", "color": [0.1490196078431373, 0.1490196078431373, 0.1568627450980392, 1], "label": 1}, {"id": "0842D788-89E8-4F18-A94C-7671F41BBD7D", "name": "Oval Copy 4", "rect": {"x": 133, "y": 395, "width": 10, "height": 10}, "_class": "shapeGroup", "color": [0.1490196078431373, 0.1490196078431373, 0.1568627450980392, 1], "label": 1}, {"id": "0D433E9F-D586-42E6-BC51-B607A3FC8602", "name": "Oval Copy 5", "rect": {"x": 150, "y": 395, "width": 10, "height": 10}, "_class": "shapeGroup", "color": [0.1490196078431373, 0.1490196078431373, 0.1568627450980392, 1], "label": 1}, {"id": "B7836690-3525-4D79-8D20-D5ED6CA69352", "name": "Rectangle Copy 2", "rect": {"x": 50, "y": 481, "width": 276, "height": 50}, "_class": "shapeGroup", "color": [0.9607843137254902, 0.9607843137254902, 0.9607843137254902, 1], "label": 1}, {"id": "FEF66674-626B-43AF-945C-D07259AC0576", "name": "Sign In", "rect": {"x": 161, "y": 497, "width": 55, "height": 18}, "_class": "text", "color": [0.0, 0.0, 0.0, 0.0], "label": 1}, {"id": "BAD8E029-15FC-4A61-9112-61A8421AABBA", "name": "Oval", "rect": {"x": 88, "y": 679, "width": 50, "height": 50}, "_class": "shapeGroup", "color": [0.1490196078431373, 0.4470588235294119, 0.796078431372549, 1], "label": 1}, {"id": "DBA4564F-DDF8-4671-9DFF-A754A56142EC", "name": "Path", "rect": {"x": 106.75, "y": 692.75, "width": 12.5, "height": 25}, "_class": "shapeGroup", "color": [1, 1, 1, 1], "label": 1}, {"id": "1EFC4698-6C44-43E1-A31C-44C4776C8EA2", "name": "Oval", "rect": {"x": 238, "y": 679, "width": 50, "height": 50}, "_class": "shapeGroup", "color": [0.9882352941176471, 0.2196078431372549, 0.3137254901960782, 1], "label": 1}, {"id": "E6EBE8BB-E1DC-425E-A811-AE8DF41F9416", "name": "Path", "rect": {"x": 252.96841430664062, "y": 692.360369001116, "width": 16.291061401367188, "height": 25.779261997767776}, "_class": "shapePath", "color": [0.0, 0.0, 0.0, 0.0], "label": 1}, {"id": "E1A835B3-B0CF-4E83-AC95-80354071F346", "name": "Path", "rect": {"x": 257.9810485839844, "y": 694.329618181501, "width": 6.086770193917346, "height": 8.235042027064765}, "_class": "shapePath", "color": [0.0, 0.0, 0.0, 0.0], "label": 1}, {"id": "B1EB69FE-E09E-4BA9-B96A-24C974406E6B", "name": "Path", "rect": {"x": 256.5488673618861, "y": 708.4724077497209, "width": 9.667223249163044, "height": 7.518951416015625}, "_class": "shapePath", "color": [0.0, 0.0, 0.0, 0.0], "label": 1}, {"id": "3643A9C4-9576-4FC3-997F-C59A58B01C50", "name": "Path", "rect": {"x": 269.0804530552457, "y": 699.8793204171317, "width": 8.951132638113904, "height": 8.951132638113904}, "_class": "shapeGroup", "color": [1, 1, 1, 1], "label": 1}, {"id": "B3D3E0E8-6CF6-4986-958B-3BB5938D67CE", "name": "Oval Copy", "rect": {"x": 163, "y": 679, "width": 50, "height": 50}, "_class": "shapeGroup", "color": [0.3098039215686275, 0.7686274509803923, 1, 1], "label": 1}, {"id": "EC502E25-FCC2-4EFE-9A0A-A7F4B71A6045", "name": "Path", "rect": {"x": 175.5, "y": 694, "width": 25, "height": 20.820889058835633}, "_class": "shapeGroup", "color": [1, 1, 1, 1], "label": 1}], "width": 375, "height": 812, "layer_width": 64, "layer_height": 64}