{"layers": [{"id": "52FEC3D7-BD37-4D58-98B7-D6C68AFE94A7", "name": "Navigation/Dropdown/Light/Default", "rect": {"x": 336, "y": 837.9999999999998, "width": 104, "height": 32}, "_class": "symbolInstance", "color": [0.847, 0.847, 0.847, 1], "label": 0}, {"id": "A4C26CE8-4083-4F45-A999-99C2CC26C8E0", "name": "Navigation/Dropdown/Light/Default-Large", "rect": {"x": 336, "y": 893.9999999999998, "width": 116, "height": 40}, "_class": "symbolInstance", "color": [0.0, 0.0, 0.0, 0.0], "label": 1}, {"id": "4A391957-6056-4398-AF5C-D8399D8F8D5B", "name": "Navigation/Dropdown/Light/Default-Small", "rect": {"x": 336, "y": 789.9999999999998, "width": 92, "height": 24}, "_class": "symbolInstance", "color": [0.0, 0.0, 0.0, 0.0], "label": 1}, {"id": "E629A1AF-F2EC-4D17-91F6-0C66F538BD47", "name": "Navigation/Dropdown/Light/Primary-Small", "rect": {"x": 120, "y": 789.9999999999998, "width": 92, "height": 24}, "_class": "symbolInstance", "color": [0.0, 0.0, 0.0, 0.0], "label": 1}, {"id": "E665986C-6760-4212-B04F-536F1956B0FF", "name": "Navigation/Dropdown/Light/Primary-Default", "rect": {"x": 120, "y": 837.9999999999998, "width": 104, "height": 32}, "_class": "symbolInstance", "color": [0.0, 0.0, 0.0, 0.0], "label": 1}, {"id": "85C016BB-867B-4B70-B963-0DDC75037B27", "name": "Navigation/Dropdown/Light/Primary-Large", "rect": {"x": 120, "y": 893.9999999999998, "width": 116, "height": 40}, "_class": "symbolInstance", "color": [0.0, 0.0, 0.0, 0.0], "label": 1}, {"id": "CD50A7DD-8DFD-4C06-A916-D7E601E966E3", "name": "Navigation/Dropdown/Light/Text-Small", "rect": {"x": 552, "y": 789.9999999999998, "width": 92, "height": 24}, "_class": "symbolInstance", "color": [0.0, 0.0, 0.0, 0.0], "label": 1}, {"id": "399A4EA4-1EE6-457E-BF8C-00F8CFCFEA21", "name": "Navigation/Dropdown/Light/Text-Default", "rect": {"x": 552, "y": 837.9999999999998, "width": 92, "height": 32}, "_class": "symbolInstance", "color": [0.0, 0.0, 0.0, 0.0], "label": 1}, {"id": "5F18A595-CE77-470B-91FB-179819F60E74", "name": "Navigation/Dropdown/Light/Text-Large", "rect": {"x": 552, "y": 893.9999999999998, "width": 116, "height": 40}, "_class": "symbolInstance", "color": [0.0, 0.0, 0.0, 0.0], "label": 1}, {"id": "F3938BCB-E8E5-48CF-B9FD-C11A6CB5D015", "name": "Navigation/Dropdown/Light/Option", "rect": {"x": 732, "y": 762.9999999999998, "width": 168, "height": 176}, "_class": "symbolInstance", "color": [0.0, 0.0, 0.0, 0.0], "label": 1}, {"id": "8AFE5E6A-D3BD-49CA-8686-C1B2709428DB", "name": "Dropdown \u4e0b\u62c9\u83dc\u5355", "rect": {"x": 120, "y": 725.9999999999998, "width": 147, "height": 24}, "_class": "text", "color": [0.0, 0.0, 0.0, 0.0], "label": 1}, {"id": "D662F754-2F6D-4CB7-A006-6836E67A05CA", "name": "\u77e9\u5f62", "rect": {"x": 120, "y": 1098.0, "width": 1232, "height": 174}, "_class": "rectangle", "color": [0, 0, 0, 0.04], "label": 1}, {"id": "5C94235E-361A-42FC-9007-6C166BCC90BC", "name": "Breadcrumber/Default", "rect": {"x": 144, "y": 1122.0, "width": 218, "height": 22}, "_class": "symbolInstance", "color": [0.0, 0.0, 0.0, 0.0], "label": 1}, {"id": "690C909B-AFB7-44CE-92E8-AAD1DC256F50", "name": "\u77e9\u5f62", "rect": {"x": 144, "y": 1196.0, "width": 840, "height": 52}, "_class": "rectangle", "color": [0.0, 0.0, 0.0, 0.0], "label": 1}, {"id": "9EA7E68F-9CC1-4488-B7CA-C3E1034624AE", "name": "\u751f\u6548\u65e5\u671f:", "rect": {"x": 424, "y": 1226.0, "width": 64, "height": 22}, "_class": "text", "color": [0.0, 0.0, 0.0, 0.0], "label": 1}, {"id": "B3742E99-A793-485A-9349-BE18A694E7D0", "name": "2017-01-10 \uff5e 2017-01", "rect": {"x": 492, "y": 1226.0, "width": 174, "height": 22}, "_class": "text", "color": [0.0, 0.0, 0.0, 0.0], "label": 1}, {"id": "71992529-6760-4B57-9C85-0B42413A44E5", "name": "\u521b\u5efa\u65f6\u95f4:", "rect": {"x": 144, "y": 1226.0, "width": 64, "height": 22}, "_class": "text", "color": [0.0, 0.0, 0.0, 0.0], "label": 1}, {"id": "505C1575-B2BC-46DC-B066-6C640656CF36", "name": "2017-01-10", "rect": {"x": 212, "y": 1226.0, "width": 76, "height": 22}, "_class": "text", "color": [0.0, 0.0, 0.0, 0.0], "label": 1}, {"id": "A66737CB-105F-41A4-9152-63184C77994D", "name": "\u5173\u8054\u5355\u636e:", "rect": {"x": 424, "y": 1196.0, "width": 64, "height": 22}, "_class": "text", "color": [0.0, 0.0, 0.0, 0.0], "label": 1}, {"id": "0B09095F-48F0-4DE7-8A7B-86BC8D8642AD", "name": "421421", "rect": {"x": 492, "y": 1196.0, "width": 48, "height": 22}, "_class": "text", "color": [0.0, 0.0, 0.0, 0.0], "label": 1}, {"id": "9C17EE95-5CAF-4AAA-B321-BE1021A76DF2", "name": "Content", "rect": {"x": 196, "y": 1196.0, "width": 42, "height": 22}, "_class": "text", "color": [0.0, 0.0, 0.0, 0.0], "label": 1}, {"id": "D0164949-C73D-4134-9892-C1E0BD1FEB58", "name": "Label\uff1a", "rect": {"x": 144, "y": 1196.0, "width": 48, "height": 22}, "_class": "text", "color": [0.0, 0.0, 0.0, 0.0], "label": 1}, {"id": "59B32EA9-85EA-43B1-AE2A-4B8AF2711235", "name": "Content", "rect": {"x": 772, "y": 1196.0, "width": 168, "height": 22}, "_class": "text", "color": [0.0, 0.0, 0.0, 0.0], "label": 1}, {"id": "ABE449EB-405B-4F3E-B032-254837533FB4", "name": "Label\uff1a", "rect": {"x": 704, "y": 1196.0, "width": 64, "height": 22}, "_class": "text", "color": [0.0, 0.0, 0.0, 0.0], "label": 1}, {"id": "DDF992B6-604C-412A-8213-97574DD4A57F", "name": "\u5206\u9875\u6d4f\u89c8\u8be6\u60c5", "rect": {"x": 144, "y": 1154.0, "width": 120, "height": 28}, "_class": "text", "color": [0.0, 0.0, 0.0, 0.0], "label": 1}, {"id": "0FE69E06-A6E2-46FB-8684-0083945C1ACE", "name": "General/Button/Primary/Light/Default", "rect": {"x": 1108, "y": 1152.0, "width": 88, "height": 32}, "_class": "symbolInstance", "color": [0.0, 0.0, 0.0, 0.0], "label": 1}, {"id": "D0C13FA4-0F7B-4834-A969-6651AC33A1D4", "name": "General/Button/Default/Light/Default", "rect": {"x": 1212, "y": 1152.0, "width": 88, "height": 32}, "_class": "symbolInstance", "color": [0.0, 0.0, 0.0, 0.0], "label": 1}, {"id": "7FA03FC1-39CF-4C98-8DD7-E8877F0E1222", "name": "\u77e9\u5f62", "rect": {"x": 1308, "y": 1158.0, "width": 20, "height": 20}, "_class": "rectangle", "color": [0, 0, 0, 1], "label": 1}, {"id": "3AC978A0-77C0-40E5-8283-741B7BFB1845", "name": "\u8def\u5f84", "rect": {"x": 1311.333333333333, "y": 1167.1666666666667, "width": 2.1875, "height": 2.18750004609808}, "_class": "shapePath", "color": [0, 0, 0, 0.65], "label": 1}, {"id": "9D193468-1908-419D-BA40-C0137F0DB094", "name": "\u8def\u5f84", "rect": {"x": 1316.802083333333, "y": 1167.1666666897158, "width": 2.1875, "height": 2.1875}, "_class": "shapePath", "color": [0, 0, 0, 0.65], "label": 1}, {"id": "62D2AB2D-F8DA-4BC0-B0F2-66FB5940BC18", "name": "\u8def\u5f84", "rect": {"x": 1322.270833333333, "y": 1167.1666666897158, "width": 2.1875, "height": 2.1875}, "_class": "shapePath", "color": [0, 0, 0, 0.65], "label": 1}, {"id": "392C297F-BE08-4235-A58F-8261ABD67E85", "name": "PageHeader \u9875\u5934", "rect": {"x": 120, "y": 1034.0, "width": 130, "height": 24}, "_class": "text", "color": [0.0, 0.0, 0.0, 0.0], "label": 1}, {"id": "D54DB0B6-9C33-4D82-AD3D-90637CF4FE91", "name": "Navigation/Pagination/Light/Default", "rect": {"x": 120, "y": 404.0, "width": 432, "height": 32.00000000000001}, "_class": "symbolInstance", "color": [0.0, 0.0, 0.0, 0.0], "label": 1}, {"id": "F5520143-D592-4105-93CF-8F34FF81ACF2", "name": "Navigation/Pagination/Light/More", "rect": {"x": 590, "y": 404.0, "width": 322, "height": 32}, "_class": "symbolInstance", "color": [0.0, 0.0, 0.0, 0.0], "label": 1}, {"id": "E2265ADC-C6A7-4D07-B3A5-F1C9EE1C933E", "name": "Navigation/Pagination/Light/Small 1", "rect": {"x": 936, "y": 409.0, "width": 202, "height": 22}, "_class": "symbolInstance", "color": [0.0, 0.0, 0.0, 0.0], "label": 1}, {"id": "D31D0762-F7F9-4FBE-8FA5-3BDB6426E916", "name": "Navigation/Pagination/Light/Small 2", "rect": {"x": 1164, "y": 409.0, "width": 156, "height": 22}, "_class": "symbolInstance", "color": [0.0, 0.0, 0.0, 0.0], "label": 1}, {"id": "2B45F24E-4850-4EA6-AF53-3A8683A3E259", "name": "Pagination \u5206\u9875", "rect": {"x": 120, "y": 340.0, "width": 118, "height": 24}, "_class": "text", "color": [0.0, 0.0, 0.0, 0.0], "label": 1}, {"id": "1A5F16C8-B8E9-431D-B3CF-6DEC5BC2A6A3", "name": "Navigation/Side/Light/Default", "rect": {"x": 120, "y": 2238.5882352941176, "width": 208, "height": 409.4117647058822}, "_class": "symbolInstance", "color": [0.847, 0.847, 0.847, 1], "label": 1}, {"id": "EDECC167-8B70-43EC-B93E-5947200C30B7", "name": "Side Menu \u4fa7\u8fb9\u5bfc\u822a", "rect": {"x": 120, "y": 2182.235294117647, "width": 150, "height": 24}, "_class": "text", "color": [0.0, 0.0, 0.0, 0.0], "label": 1}, {"id": "7770A390-4D9A-4BA0-8369-46432C035437", "name": "Steps \u6b65\u9aa4\u6761", "rect": {"x": 120, "y": 1430.0000000000005, "width": 97, "height": 24}, "_class": "text", "color": [0.0, 0.0, 0.0, 0.0], "label": 1}, {"id": "7261B749-1D6E-4AFE-AD6D-E36B073F9D06", "name": "\u5bfc\u822a/Steps\u6b65\u9aa4\u6761/Light/\u6c34\u5e73-\u5f53\u524d\u9879", "rect": {"x": 120, "y": 1491.9999999999998, "width": 352, "height": 32}, "_class": "symbolInstance", "color": [0.0, 0.0, 0.0, 0.0], "label": 1}, {"id": "CB1E1329-A7B3-440D-8933-916328986495", "name": "\u5bfc\u822a/Steps\u6b65\u9aa4\u6761/Light/\u6c34\u5e73-\u5f85\u5904\u7406", "rect": {"x": 480, "y": 1491.9999999999998, "width": 352, "height": 32}, "_class": "symbolInstance", "color": [0.0, 0.0, 0.0, 0.0], "label": 1}, {"id": "D314C8DD-E280-4240-8C2E-66831C9D32D1", "name": "\u5bfc\u822a/Steps\u6b65\u9aa4\u6761/Light/\u6c34\u5e73-\u5f85\u5904\u7406\u5907\u4efd", "rect": {"x": 840, "y": 1491.9999999999998, "width": 104, "height": 32}, "_class": "symbolInstance", "color": [0.0, 0.0, 0.0, 0.0], "label": 1}, {"id": "CD8FA2BB-3BD6-457D-9EF4-1B571DAC59CA", "name": "\u5bfc\u822a/Steps\u6b65\u9aa4\u6761/Light/\u6c34\u5e73-\u5f53\u524d\u9879", "rect": {"x": 481, "y": 1547.9999999999998, "width": 352, "height": 32}, "_class": "symbolInstance", "color": [0.0, 0.0, 0.0, 0.0], "label": 1}, {"id": "EEEE47B3-C717-4F00-9300-649E616B2FD9", "name": "\u5bfc\u822a/Steps\u6b65\u9aa4\u6761/Light/\u6c34\u5e73-\u5f85\u5904\u7406\u5907\u4efd", "rect": {"x": 840, "y": 1548.0, "width": 104, "height": 32}, "_class": "symbolInstance", "color": [0.0, 0.0, 0.0, 0.0], "label": 1}, {"id": "F773BC92-4448-49FC-A2AF-FFCC9D5AABA7", "name": "\u5bfc\u822a/Steps\u6b65\u9aa4\u6761/Light/\u6c34\u5e73-\u5b8c\u6210\u9879", "rect": {"x": 120, "y": 1547.9999999999998, "width": 352, "height": 32}, "_class": "symbolInstance", "color": [0.0, 0.0, 0.0, 0.0], "label": 1}, {"id": "817261AC-A8C8-4A0F-B0C7-54ADB948757B", "name": "\u5bfc\u822a/Steps\u6b65\u9aa4\u6761/Light/\u5c0f-\u6c34\u5e73-\u5f53\u524d\u9879", "rect": {"x": 120, "y": 1627.9999999999998, "width": 256, "height": 24}, "_class": "symbolInstance", "color": [0.0, 0.0, 0.0, 0.0], "label": 1}, {"id": "E43F91F3-2FF5-4707-B992-45083606E1DA", "name": "\u5bfc\u822a/Steps\u6b65\u9aa4\u6761/Light/\u5c0f-\u6c34\u5e73-\u5f85\u5904\u7406", "rect": {"x": 384, "y": 1627.9999999999998, "width": 256, "height": 24}, "_class": "symbolInstance", "color": [0.0, 0.0, 0.0, 0.0], "label": 1}, {"id": "A0CB5360-5503-41C3-B1E9-796406B444C8", "name": "\u5bfc\u822a/Steps\u6b65\u9aa4\u6761/Light/\u5c0f-\u6c34\u5e73-\u5f85\u5904\u7406\u5907\u4efd", "rect": {"x": 648, "y": 1627.9999999999998, "width": 88, "height": 24}, "_class": "symbolInstance", "color": [0.0, 0.0, 0.0, 0.0], "label": 1}, {"id": "E357B839-8810-4FFC-B7B4-641BF38FC577", "name": "\u5bfc\u822a/Steps\u6b65\u9aa4\u6761/Light/\u5c0f-\u6c34\u5e73-\u5f53\u524d\u9879", "rect": {"x": 384, "y": 1675.9999999999998, "width": 256, "height": 24}, "_class": "symbolInstance", "color": [0.0, 0.0, 0.0, 0.0], "label": 1}, {"id": "E4C1F3AC-F528-4FA4-AA73-A5C22C1A5742", "name": "\u5bfc\u822a/Steps\u6b65\u9aa4\u6761/Light/\u5c0f-\u6c34\u5e73-\u5b8c\u6210\u9879", "rect": {"x": 120, "y": 1676.0, "width": 256, "height": 24}, "_class": "symbolInstance", "color": [0.0, 0.0, 0.0, 0.0], "label": 1}, {"id": "D3EDD322-DD50-4C9A-9A82-BE49922A9053", "name": "\u5bfc\u822a/Steps\u6b65\u9aa4\u6761/Light/\u5c0f-\u6c34\u5e73-\u5f85\u5904\u7406\u5907\u4efd", "rect": {"x": 648, "y": 1675.9999999999998, "width": 88, "height": 24}, "_class": "symbolInstance", "color": [0.0, 0.0, 0.0, 0.0], "label": 1}, {"id": "E21CF963-9B79-4343-9BBD-C0469D5FE413", "name": "\u5bfc\u822a/Steps\u6b65\u9aa4\u6761/Light/\u6c34\u5e73-\u5e26\u63cf\u8ff0-\u5f53\u524d\u9879", "rect": {"x": 400, "y": 1747.9999999999998, "width": 272, "height": 75.99999999999977}, "_class": "symbolInstance", "color": [0.0, 0.0, 0.0, 0.0], "label": 1}, {"id": "F0BCD1EC-55EC-4F23-8574-7D060E06E337", "name": "\u5bfc\u822a/Steps\u6b65\u9aa4\u6761/Light/\u6c34\u5e73-\u5e26\u63cf\u8ff0-\u5b8c\u6210\u9879", "rect": {"x": 120, "y": 1747.9999999999998, "width": 272, "height": 75.99999999999977}, "_class": "symbolInstance", "color": [0.0, 0.0, 0.0, 0.0], "label": 1}, {"id": "D9F1CD63-CB1C-4A4D-AF6F-4E1AC42F7BE6", "name": "\u5bfc\u822a/Steps\u6b65\u9aa4\u6761/Light/\u6c34\u5e73-\u5e26\u63cf\u8ff0-\u5f85\u5904\u7406", "rect": {"x": 680, "y": 1747.9999999999998, "width": 200, "height": 75.99999999999977}, "_class": "symbolInstance", "color": [0.0, 0.0, 0.0, 0.0], "label": 1}, {"id": "98331E33-C88B-4952-A144-BF8CDB9A5844", "name": "\u5bfc\u822a/Steps\u6b65\u9aa4\u6761/Light/\u5782\u76f4-\u5e26\u63cf\u8ff0-\u5b8c\u6210\u9879", "rect": {"x": 118, "y": 1876.0, "width": 172, "height": 72}, "_class": "symbolInstance", "color": [0.0, 0.0, 0.0, 0.0], "label": 1}, {"id": "7753E813-D9A3-4E81-8916-69C4479A6108", "name": "\u5bfc\u822a/Steps\u6b65\u9aa4\u6761/Light/\u5782\u76f4-\u5e26\u63cf\u8ff0-\u7b49\u5f85\u5904\u7406", "rect": {"x": 118, "y": 2035.9999999999998, "width": 172, "height": 53.99999999999977}, "_class": "symbolInstance", "color": [0.0, 0.0, 0.0, 0.0], "label": 1}, {"id": "5F1554C0-D850-4562-AD81-F3EF9E1C55F6", "name": "\u5bfc\u822a/Steps\u6b65\u9aa4\u6761/Light/\u5782\u76f4-\u5e26\u63cf\u8ff0-\u5f53\u524d\u9879", "rect": {"x": 118, "y": 1955.9999999999998, "width": 172, "height": 72}, "_class": "symbolInstance", "color": [0.0, 0.0, 0.0, 0.0], "label": 1}, {"id": "62283490-7BE9-4ABE-869C-6E0A7B944CAD", "name": "\u5bfc\u822a/Steps\u6b65\u9aa4\u6761/Light/\u5c0f-\u5782\u76f4-\u5e26\u63cf\u8ff0-\u5b8c\u6210\u9879", "rect": {"x": 404, "y": 1875.0, "width": 164, "height": 65}, "_class": "symbolInstance", "color": [0.0, 0.0, 0.0, 0.0], "label": 1}, {"id": "EB161CEE-5846-4C21-995E-15F150696523", "name": "\u5bfc\u822a/Steps\u6b65\u9aa4\u6761/Light/\u5c0f-\u5782\u76f4-\u5e26\u63cf\u8ff0-\u5f53\u524d\u9879", "rect": {"x": 404, "y": 1948.0, "width": 164, "height": 64}, "_class": "symbolInstance", "color": [0.0, 0.0, 0.0, 0.0], "label": 1}, {"id": "5EA1CEBE-E49D-4C9C-8720-3AA5FB8F0C51", "name": "\u5bfc\u822a/Steps\u6b65\u9aa4\u6761/Light/\u5c0f-\u5782\u76f4-\u5e26\u63cf\u8ff0-\u5f85\u5904\u7406", "rect": {"x": 404, "y": 2019.9999999999995, "width": 164, "height": 48}, "_class": "symbolInstance", "color": [0.0, 0.0, 0.0, 0.0], "label": 1}, {"id": "B1728C31-41FD-47DF-A9FB-53F80B3F4D99", "name": "Navigation/BackTop/Light/Circle", "rect": {"x": 880, "y": 2260.0, "width": 40, "height": 40}, "_class": "symbolInstance", "color": [0.0, 0.0, 0.0, 0.0], "label": 1}, {"id": "895AA0DE-C485-484A-926C-33E3DEB615AE", "name": "Anchor \u951a\u70b9", "rect": {"x": 880, "y": 2184.0, "width": 137, "height": 24}, "_class": "text", "color": [0.0, 0.0, 0.0, 0.0], "label": 1}, {"id": "B9D42C02-C38F-41F2-AB68-FF16CE2E86AC", "name": "Navigation/BackTop/Light/Square", "rect": {"x": 880, "y": 2348.0, "width": 40, "height": 40}, "_class": "symbolInstance", "color": [0.0, 0.0, 0.0, 0.0], "label": 1}, {"id": "0F48290E-9E76-4107-81DC-015FCA20D51B", "name": "Navigation/Anchor/Light/Vertical", "rect": {"x": 528, "y": 2248.0, "width": 152, "height": 135}, "_class": "symbolInstance", "color": [0.0, 0.0, 0.0, 0.0], "label": 1}, {"id": "6BFB5645-D232-4688-9F45-38C85CC88B9D", "name": "Anchor \u951a\u70b9", "rect": {"x": 530, "y": 2184.0, "width": 91, "height": 24}, "_class": "text", "color": [0.0, 0.0, 0.0, 0.0], "label": 1}, {"id": "D792F0B5-357C-4B12-B05C-295C168C9E1A", "name": "\u5bfc\u822a/Tabs\u6807\u7b7e\u9875/\u4eae\u8272/2", "rect": {"x": 470, "y": 591.9999999999998, "width": 311, "height": 34}, "_class": "symbolInstance", "color": [0.0, 0.0, 0.0, 0.0], "label": 1}, {"id": "CA535148-5DED-40B3-B594-58E8D541FCEE", "name": "\u5bfc\u822a/Tabs\u6807\u7b7e\u9875/\u4eae\u8272/3", "rect": {"x": 910, "y": 585.9999999999998, "width": 322, "height": 40}, "_class": "symbolInstance", "color": [0.0, 0.0, 0.0, 0.0], "label": 1}, {"id": "A53AF132-A666-47FF-83D3-F85DE424BDD0", "name": "Tabs \u6807\u7b7e\u9875", "rect": {"x": 120, "y": 535.9999999999998, "width": 91, "height": 24}, "_class": "text", "color": [0.0, 0.0, 0.0, 0.0], "label": 1}, {"id": "4F959AC7-6FFC-4B11-89A1-50D8F7C95381", "name": "\u5bfc\u822a/Tabs\u6807\u7b7e\u9875/\u4eae\u8272/1", "rect": {"x": 120, "y": 590.9999999999999, "width": 251, "height": 34.000000000000114}, "_class": "symbolInstance", "color": [0.0, 0.0, 0.0, 0.0], "label": 1}, {"id": "9D2538FF-AA70-4B87-8418-65855BC5E527", "name": "Ant Design Component", "rect": {"x": 120, "y": 166.2881355932202, "width": 1200, "height": 22}, "_class": "text", "color": [0.0, 0.0, 0.0, 0.0], "label": 1}, {"id": "6879B634-4C74-4740-98EB-8E989AB1928C", "name": "Components Navigatio", "rect": {"x": 120, "y": 102.37288135593207, "width": 242, "height": 40}, "_class": "text", "color": [0.0, 0.0, 0.0, 0.0], "label": 1}, {"id": "3BB7399C-F644-44DB-AAE5-E25950D83121", "name": "Divider Color", "rect": {"x": 120, "y": 217.96610169491512, "width": 1200, "height": 4.067796610169495}, "_class": "rectangle", "color": [0, 0, 0, 0.06], "label": 1}, {"id": "759FB1D4-1611-42EC-91B3-E55D3679E58D", "name": "Divider Color", "rect": {"x": 120, "y": 2748.0, "width": 1200, "height": 4}, "_class": "rectangle", "color": [0, 0, 0, 0.06], "label": 1}, {"id": "00456FAC-1097-409E-84B2-E472965044A2", "name": "Ant Design \u4f01\u4e1a\u7ea7\u4ea7\u54c1\u8bbe\u8ba1\u4f53\u7cfb", "rect": {"x": 120, "y": 2776.0, "width": 370, "height": 22}, "_class": "text", "color": [0.0, 0.0, 0.0, 0.0], "label": 1}, {"id": "D7ACC264-CECB-4387-8D2A-4C09410C5286", "name": "Ant Design Component", "rect": {"x": 1109, "y": 2776.0, "width": 211, "height": 22}, "_class": "text", "color": [0.0, 0.0, 0.0, 0.0], "label": 1}], "width": 1440, "height": 2898, "layer_width": 64, "layer_height": 64}