{"layers": [{"id": "199B0C59-7DB3-4FB4-A05B-18F322065205", "name": "Back", "rect": {"x": 0, "y": 0, "width": 375, "height": 667}, "_class": "shapeGroup", "color": [0.02120719942933202, 0.007009074375538174, 0.05832801870748299, 1], "label": 0}, {"id": "6EF8159F-D87D-43E7-9F18-BBDCA4D1DCE4", "name": "Base", "rect": {"x": 0, "y": 447, "width": 375, "height": 85}, "_class": "shapeGroup", "color": [0.0, 0.0, 0.0, 0.0], "label": 1}, {"id": "D94D77C8-49CE-4644-BDBC-70B3AF183123", "name": "L Caption", "rect": {"x": 30, "y": 495, "width": 252, "height": 16}, "_class": "text", "color": [0.0, 0.0, 0.0, 0.0], "label": 1}, {"id": "F380F951-827C-4F77-AADB-12CD0B9FCAB6", "name": "L Text", "rect": {"x": 30, "y": 467, "width": 54, "height": 20}, "_class": "text", "color": [0.0, 0.0, 0.0, 0.0], "label": 1}, {"id": "FA99C70E-E340-4606-AA90-7337F4591875", "name": "Icon Copy", "rect": {"x": 339, "y": 484, "width": 6.061493656929088, "height": 11.249390095108538}, "_class": "symbolInstance", "color": [0.0, 0.0, 0.0, 0.0], "label": 1}, {"id": "DAB40BF2-1E50-41B7-B02B-36CBC5154BCA", "name": "Line", "rect": {"x": 30, "y": 531, "width": 315, "height": 1}, "_class": "shapeGroup", "color": [0.1181483562230963, 0.109325208410335, 0.1652051445578231, 1], "label": 1}, {"id": "D5ACB84D-545F-4984-BAA2-6739AA8B1146", "name": "Base", "rect": {"x": 0, "y": 532, "width": 375, "height": 85}, "_class": "shapeGroup", "color": [0.0, 0.0, 0.0, 0.0], "label": 1}, {"id": "D58444DC-C561-40A6-870D-E3738300852B", "name": "L Caption", "rect": {"x": 30, "y": 580, "width": 278, "height": 16}, "_class": "text", "color": [0.0, 0.0, 0.0, 0.0], "label": 1}, {"id": "F3F1FC69-EC1D-4992-96EF-0614E74656FB", "name": "L Text", "rect": {"x": 30, "y": 552, "width": 42, "height": 20}, "_class": "text", "color": [0.0, 0.0, 0.0, 0.0], "label": 1}, {"id": "92CFC5E9-DD49-4FE3-AD90-A6BBCD594D5D", "name": "Icon Copy", "rect": {"x": 339, "y": 569, "width": 6.061493656929088, "height": 11.249390095108538}, "_class": "symbolInstance", "color": [0.0, 0.0, 0.0, 0.0], "label": 1}, {"id": "D295F9B7-C6CE-4871-BF7A-A1D4D592DEA1", "name": "Line", "rect": {"x": 30, "y": 616, "width": 315, "height": 1}, "_class": "shapeGroup", "color": [0.1181483562230963, 0.109325208410335, 0.1652051445578231, 1], "label": 1}, {"id": "8D6EC7EC-D2A6-43A1-8AA7-833A99D30E35", "name": "Transactions", "rect": {"x": 30, "y": 423, "width": 118, "height": 24}, "_class": "text", "color": [0.0, 0.0, 0.0, 0.0], "label": 1}, {"id": "67EA0B77-255C-43DA-AE89-6B021A4371C4", "name": "2", "rect": {"x": 160, "y": 423, "width": 12, "height": 24}, "_class": "text", "color": [0.0, 0.0, 0.0, 0.0], "label": 1}, {"id": "FD0CBB5C-EAC2-4ECB-AE8B-3751F6F6688F", "name": "Icons/Top/Search", "rect": {"x": 324, "y": 428, "width": 16.707106781186553, "height": 16.707106781186667}, "_class": "symbolInstance", "color": [0.0, 0.0, 0.0, 0.0], "label": 1}, {"id": "955BD5A6-DD66-441F-951E-3CDAB9D6C583", "name": "Shape", "rect": {"x": 0, "y": 285, "width": 163, "height": 49}, "_class": "shapeGroup", "color": [0.1181483562230963, 0.109325208410335, 0.1652051445578231, 1], "label": 1}, {"id": "AF637EE8-07F6-4C71-9683-1FDC3F0C2AC4", "name": "Shape", "rect": {"x": 163, "y": 236, "width": 212, "height": 49}, "_class": "shapeGroup", "color": [0.1181483562230963, 0.109325208410335, 0.1652051445578231, 1], "label": 1}, {"id": "2E27536B-58BC-4C97-A421-29715E2FCCD0", "name": "Date", "rect": {"x": 323, "y": 349, "width": 23, "height": 20}, "_class": "symbolInstance", "color": [0.0, 0.0, 0.0, 0.0], "label": 1}, {"id": "C8396029-E267-45E1-947B-EAB53B6B62BB", "name": "Date", "rect": {"x": 274, "y": 349, "width": 23, "height": 20}, "_class": "symbolInstance", "color": [0.0, 0.0, 0.0, 0.0], "label": 1}, {"id": "E5638669-6DC8-4EC3-9AF1-A0957A304A91", "name": "Date", "rect": {"x": 225, "y": 349, "width": 23, "height": 20}, "_class": "symbolInstance", "color": [0.0, 0.0, 0.0, 0.0], "label": 1}, {"id": "7E53B5DE-9F0B-46F5-AB10-A7E341BB2704", "name": "Date", "rect": {"x": 176, "y": 349, "width": 23, "height": 20}, "_class": "symbolInstance", "color": [0.0, 0.0, 0.0, 0.0], "label": 1}, {"id": "6AADFBCB-98BE-488F-8BBD-842C51EF998D", "name": "Date", "rect": {"x": 127, "y": 349, "width": 23, "height": 20}, "_class": "symbolInstance", "color": [0.0, 0.0, 0.0, 0.0], "label": 1}, {"id": "80F66DAF-E3F1-4170-A4A5-90900588001D", "name": "Date", "rect": {"x": 78, "y": 349, "width": 23, "height": 20}, "_class": "symbolInstance", "color": [0.0, 0.0, 0.0, 0.0], "label": 1}, {"id": "0F4B1014-1BD3-4580-9E8F-597C299AC08E", "name": "Date", "rect": {"x": 29, "y": 349, "width": 23, "height": 20}, "_class": "symbolInstance", "color": [0.0, 0.0, 0.0, 0.0], "label": 1}, {"id": "A631B8F1-9CB5-4141-A154-9C4FD442E78B", "name": "Date", "rect": {"x": 323, "y": 300, "width": 23, "height": 20}, "_class": "symbolInstance", "color": [0.0, 0.0, 0.0, 0.0], "label": 1}, {"id": "7B410008-FADF-4260-9431-ED2EFA7A8A61", "name": "Date", "rect": {"x": 274, "y": 300, "width": 23, "height": 20}, "_class": "symbolInstance", "color": [0.0, 0.0, 0.0, 0.0], "label": 1}, {"id": "CFDAFF22-1C26-4E80-8C9A-DFB24C16372A", "name": "Date", "rect": {"x": 225, "y": 300, "width": 23, "height": 20}, "_class": "symbolInstance", "color": [0.0, 0.0, 0.0, 0.0], "label": 1}, {"id": "71439190-C899-4CE2-812D-9019A8AB7CAE", "name": "Date", "rect": {"x": 176, "y": 300, "width": 23, "height": 20}, "_class": "symbolInstance", "color": [0.0, 0.0, 0.0, 0.0], "label": 1}, {"id": "629599B8-5030-4DF6-9FF3-9120A7634429", "name": "Date", "rect": {"x": 114, "y": 285, "width": 49, "height": 49}, "_class": "symbolInstance", "color": [0.0, 0.0, 0.0, 0.0], "label": 1}, {"id": "4915CAF8-837E-4D00-9240-3D0B9657C1F3", "name": "Date", "rect": {"x": 78, "y": 300, "width": 23, "height": 20}, "_class": "symbolInstance", "color": [0.0, 0.0, 0.0, 0.0], "label": 1}, {"id": "C83087D8-C884-4CC7-BEB6-CE8B58616BA3", "name": "Date", "rect": {"x": 29, "y": 300, "width": 23, "height": 20}, "_class": "symbolInstance", "color": [0.0, 0.0, 0.0, 0.0], "label": 1}, {"id": "8CF999D5-2561-42BE-96AA-96FB1A227410", "name": "Date", "rect": {"x": 323, "y": 251, "width": 23, "height": 20}, "_class": "symbolInstance", "color": [0.0, 0.0, 0.0, 0.0], "label": 1}, {"id": "FF07EF55-40E9-497D-A714-DE7B2135B294", "name": "Date", "rect": {"x": 274, "y": 251, "width": 23, "height": 20}, "_class": "symbolInstance", "color": [0.0, 0.0, 0.0, 0.0], "label": 1}, {"id": "57D48969-7257-4A2B-9962-AB7B9EFA3D84", "name": "Date", "rect": {"x": 225, "y": 251, "width": 23, "height": 25}, "_class": "symbolInstance", "color": [0.0, 0.0, 0.0, 0.0], "label": 1}, {"id": "97805F23-86CF-4090-A740-0928F92698B0", "name": "Date", "rect": {"x": 176, "y": 251, "width": 23, "height": 20}, "_class": "symbolInstance", "color": [0.0, 0.0, 0.0, 0.0], "label": 1}, {"id": "685D2E53-C24A-4E40-874A-57D1CC729B73", "name": "Date", "rect": {"x": 127, "y": 251, "width": 23, "height": 20}, "_class": "symbolInstance", "color": [0.0, 0.0, 0.0, 0.0], "label": 1}, {"id": "92ADEA0E-EFA4-4F87-8626-02E759784B48", "name": "Date", "rect": {"x": 78, "y": 251, "width": 23, "height": 20}, "_class": "symbolInstance", "color": [0.0, 0.0, 0.0, 0.0], "label": 1}, {"id": "A9F9E41B-2E63-47AD-9B6F-554E710F45B1", "name": "Date", "rect": {"x": 29, "y": 251, "width": 23, "height": 20}, "_class": "symbolInstance", "color": [0.0, 0.0, 0.0, 0.0], "label": 1}, {"id": "F46C081C-1A23-4212-8951-3124864D61F5", "name": "Date", "rect": {"x": 323, "y": 202, "width": 23, "height": 20}, "_class": "symbolInstance", "color": [0.0, 0.0, 0.0, 0.0], "label": 1}, {"id": "32E50529-47EE-49C5-956A-ED54C705DDA5", "name": "Date", "rect": {"x": 274, "y": 202, "width": 23, "height": 20}, "_class": "symbolInstance", "color": [0.0, 0.0, 0.0, 0.0], "label": 1}, {"id": "2C550BA2-0E87-4E25-A039-9AE88600157E", "name": "Date", "rect": {"x": 225, "y": 202, "width": 23, "height": 20}, "_class": "symbolInstance", "color": [0.0, 0.0, 0.0, 0.0], "label": 1}, {"id": "FBE450D9-A8DF-4C80-8A44-50C47FAA329E", "name": "Date", "rect": {"x": 176, "y": 202, "width": 23, "height": 20}, "_class": "symbolInstance", "color": [0.0, 0.0, 0.0, 0.0], "label": 1}, {"id": "A5C46A11-ABE1-4D22-85D9-A11658F8D056", "name": "Date", "rect": {"x": 127, "y": 202, "width": 23, "height": 20}, "_class": "symbolInstance", "color": [0.0, 0.0, 0.0, 0.0], "label": 1}, {"id": "BA5A2684-F22C-423C-AA2D-C09BFBB3C29A", "name": "Date", "rect": {"x": 78, "y": 202, "width": 23, "height": 25}, "_class": "symbolInstance", "color": [0.0, 0.0, 0.0, 0.0], "label": 1}, {"id": "AA16B1A3-9ACB-4A40-B9C9-E2086A41BE44", "name": "Date", "rect": {"x": 29, "y": 202, "width": 23, "height": 25}, "_class": "symbolInstance", "color": [0.0, 0.0, 0.0, 0.0], "label": 1}, {"id": "118F34DA-8C1A-4B47-BC90-0486B4BADF50", "name": "Date", "rect": {"x": 323, "y": 153, "width": 23, "height": 20}, "_class": "symbolInstance", "color": [0.0, 0.0, 0.0, 0.0], "label": 1}, {"id": "C2B8D1ED-8476-498C-B69B-C351BA542287", "name": "Date", "rect": {"x": 274, "y": 153, "width": 23, "height": 20}, "_class": "symbolInstance", "color": [0.0, 0.0, 0.0, 0.0], "label": 1}, {"id": "46E693B6-EC90-4C65-BF27-DF0C64CFFF04", "name": "Date", "rect": {"x": 225, "y": 153, "width": 23, "height": 20}, "_class": "symbolInstance", "color": [0.0, 0.0, 0.0, 0.0], "label": 1}, {"id": "6022D535-51FC-4291-B808-64B01FD7AC74", "name": "Date", "rect": {"x": 176, "y": 153, "width": 23, "height": 20}, "_class": "symbolInstance", "color": [0.0, 0.0, 0.0, 0.0], "label": 1}, {"id": "5999A6FC-BB81-4B4C-AB54-0503B6BA2FFA", "name": "Date", "rect": {"x": 127, "y": 153, "width": 23, "height": 20}, "_class": "symbolInstance", "color": [0.0, 0.0, 0.0, 0.0], "label": 1}, {"id": "AD8E39FF-A468-4501-817F-531EFAB9A642", "name": "Date", "rect": {"x": 78, "y": 153, "width": 23, "height": 20}, "_class": "symbolInstance", "color": [0.0, 0.0, 0.0, 0.0], "label": 1}, {"id": "AB9D7F6B-8086-47EB-BE78-FF6B99EB5D41", "name": "Date", "rect": {"x": 29, "y": 153, "width": 23, "height": 20}, "_class": "symbolInstance", "color": [0.0, 0.0, 0.0, 0.0], "label": 1}, {"id": "7CC065A2-531E-4DE8-9DCD-58D7865E333D", "name": "Week", "rect": {"x": 36.5, "y": 120, "width": 8, "height": 15}, "_class": "symbolInstance", "color": [0.0, 0.0, 0.0, 0.0], "label": 1}, {"id": "3C7349F9-F3E8-4D63-8409-22237AF4FCDD", "name": "Week", "rect": {"x": 84, "y": 120, "width": 11, "height": 15}, "_class": "symbolInstance", "color": [0.0, 0.0, 0.0, 0.0], "label": 1}, {"id": "12A2A12E-02C4-4393-95E0-264C77D35D64", "name": "Week", "rect": {"x": 134.5, "y": 120, "width": 8, "height": 15}, "_class": "symbolInstance", "color": [0.0, 0.0, 0.0, 0.0], "label": 1}, {"id": "90F0B140-7AF6-484F-ACE5-0D8DA2F895AA", "name": "Week", "rect": {"x": 181.5, "y": 120, "width": 12, "height": 15}, "_class": "symbolInstance", "color": [0.0, 0.0, 0.0, 0.0], "label": 1}, {"id": "1B53BA72-6343-432E-AD0D-A3A6F856CDE4", "name": "Week", "rect": {"x": 232.5, "y": 120, "width": 8, "height": 15}, "_class": "symbolInstance", "color": [0.0, 0.0, 0.0, 0.0], "label": 1}, {"id": "83B96D56-F418-418B-A922-05246EA08629", "name": "Week", "rect": {"x": 282, "y": 120, "width": 7, "height": 15}, "_class": "symbolInstance", "color": [0.0, 0.0, 0.0, 0.0], "label": 1}, {"id": "845EDD9E-518A-420E-BCB1-2E749CD02F79", "name": "Week", "rect": {"x": 330.5, "y": 120, "width": 8, "height": 15}, "_class": "symbolInstance", "color": [0.0, 0.0, 0.0, 0.0], "label": 1}, {"id": "95D70B61-9DC9-4267-8C9F-125FC8340284", "name": "Header/Center", "rect": {"x": 33, "y": 33, "width": 307, "height": 20.00176301481406}, "_class": "symbolInstance", "color": [0.0, 0.0, 0.0, 0.0], "label": 1}, {"id": "AC2582F8-A052-442E-BBBC-0A04CEBCDE4A", "name": "Forms/Dropdown Selected", "rect": {"x": 131, "y": 36, "width": 105, "height": 15}, "_class": "symbolInstance", "color": [0.0, 0.0, 0.0, 0.0], "label": 1}, {"id": "5D87F733-B89E-4E07-8A14-D888760B63B7", "name": "Navbar/4 icons", "rect": {"x": 0, "y": 613, "width": 375, "height": 54}, "_class": "symbolInstance", "color": [0.0, 0.0, 0.0, 0.0], "label": 1}, {"id": "94D5010D-23A8-45EB-9034-E77F00746608", "name": "Overlay", "rect": {"x": 0, "y": 0, "width": 375, "height": 667}, "_class": "shapeGroup", "color": [0.0, 0.0, 0.0, 0.0], "label": 1}, {"id": "A8A3F6A5-663A-440F-AF77-A1ECD39555E8", "name": "Shape", "rect": {"x": -51, "y": 118, "width": 379, "height": 379}, "_class": "shapeGroup", "color": [0.203921568627451, 0.6627450980392157, 1, 1], "label": 1}], "width": 375, "height": 667, "layer_width": 64, "layer_height": 64}