{"layers": [{"id": "6A99DFDA-2845-46EF-AF48-853E22E90AF0", "name": "Fill 2", "rect": {"x": 186, "y": 1282, "width": 3, "height": 9}, "_class": "shapeGroup", "color": [0, 0.4666666666666668, 1, 1], "label": 0}, {"id": "8D965BDC-9E11-4883-9605-FE3775C5DD4D", "name": "Fill 4", "rect": {"x": 191, "y": 1284, "width": 6, "height": 8}, "_class": "shapeGroup", "color": [0, 0.4666666666666668, 1, 1], "label": 1}, {"id": "E36A4C7B-AA9B-435C-BCEB-01E11C271103", "name": "Fill 6", "rect": {"x": 195, "y": 1290, "width": 8, "height": 6}, "_class": "shapeGroup", "color": [0, 0.4666666666666668, 1, 1], "label": 1}, {"id": "BFAB9C7C-EF22-4226-B053-1384B8B05A42", "name": "Fill 8", "rect": {"x": 196, "y": 1298, "width": 9, "height": 3}, "_class": "shapeGroup", "color": [0, 0.4666666666666668, 1, 1], "label": 1}, {"id": "EC7F4773-0D9B-4098-B61B-FD410D6E9EA6", "name": "Fill 10", "rect": {"x": 195, "y": 1303, "width": 8, "height": 6}, "_class": "shapeGroup", "color": [0, 0.4666666666666668, 1, 1], "label": 1}, {"id": "28439B62-473A-45D8-82CE-938B6D250522", "name": "Fill 12", "rect": {"x": 191, "y": 1307, "width": 6, "height": 8}, "_class": "shapeGroup", "color": [0, 0.4666666666666668, 1, 1], "label": 1}, {"id": "A828E2F0-228B-4C53-BFD8-EC26837180AD", "name": "Fill 14", "rect": {"x": 186, "y": 1308, "width": 3, "height": 9}, "_class": "shapeGroup", "color": [0, 0.4666666666666668, 1, 1], "label": 1}, {"id": "CA65BDBE-FC96-4609-BD10-F0B3CE50E90B", "name": "Fill 16", "rect": {"x": 178, "y": 1307, "width": 6, "height": 8}, "_class": "shapeGroup", "color": [0, 0.4666666666666668, 1, 1], "label": 1}, {"id": "27365A4E-CB84-4C13-BC27-D1744650A22F", "name": "Fill 18", "rect": {"x": 172, "y": 1303, "width": 8, "height": 6}, "_class": "shapeGroup", "color": [0, 0.4666666666666668, 1, 1], "label": 1}, {"id": "71CB2A05-69DB-44AC-B6EA-B69FE83390D7", "name": "Fill 20", "rect": {"x": 170, "y": 1298, "width": 9, "height": 3}, "_class": "shapeGroup", "color": [0, 0.4666666666666668, 1, 1], "label": 1}, {"id": "31239D6A-0EF2-4EAC-8913-ABF41A235D82", "name": "Fill 22", "rect": {"x": 172, "y": 1290, "width": 8, "height": 6}, "_class": "shapeGroup", "color": [0, 0.4666666666666668, 1, 1], "label": 1}, {"id": "5700A427-8042-4AEA-8627-A94EF292962A", "name": "Fill 24", "rect": {"x": 178, "y": 1284, "width": 6, "height": 8}, "_class": "shapeGroup", "color": [0, 0.4666666666666668, 1, 1], "label": 1}, {"id": "24374AB5-3273-4CAB-88B1-02A15914022C", "name": "9", "rect": {"x": 58.5, "y": 962.5, "width": 1, "height": 268.953125}, "_class": "shapeGroup", "color": [0.847, 0.847, 0.847, 1], "label": 1}, {"id": "47ADD127-1EE5-4DBF-A59D-C2A4F637B3C1", "name": "Jan 17", "rect": {"x": 68, "y": 961, "width": 41, "height": 19}, "_class": "text", "color": [0.0, 0.0, 0.0, 0.0], "label": 1}, {"id": "02277E51-32A2-4582-BA01-682617DF97A2", "name": "8", "rect": {"x": 177.5, "y": 962.5, "width": 1, "height": 268.953125}, "_class": "shapeGroup", "color": [0.847, 0.847, 0.847, 1], "label": 1}, {"id": "D90F01A3-A1A7-45A8-8C68-1C4AF05EC703", "name": "Feb 17", "rect": {"x": 187, "y": 961, "width": 43, "height": 19}, "_class": "text", "color": [0.0, 0.0, 0.0, 0.0], "label": 1}, {"id": "0424D972-85F2-4405-BF35-77E990999CE2", "name": "7", "rect": {"x": 296.5, "y": 962.5, "width": 1, "height": 268.953125}, "_class": "shapeGroup", "color": [0.847, 0.847, 0.847, 1], "label": 1}, {"id": "4B0A0337-1E15-4312-B952-D7352C29A0A0", "name": "Mar 17", "rect": {"x": 306, "y": 961, "width": 45, "height": 19}, "_class": "text", "color": [0.0, 0.0, 0.0, 0.0], "label": 1}, {"id": "5C23B0A1-94A3-4036-A91B-F9F625726461", "name": "6", "rect": {"x": 415.5, "y": 962.5, "width": 1, "height": 268.953125}, "_class": "shapeGroup", "color": [0.847, 0.847, 0.847, 1], "label": 1}, {"id": "FE5D9B1E-8474-47E0-865A-18BA214DB7D2", "name": "Apr 17", "rect": {"x": 425, "y": 961, "width": 42, "height": 19}, "_class": "text", "color": [0.0, 0.0, 0.0, 0.0], "label": 1}, {"id": "EF799A4F-FD2C-4B93-B9A0-79195B6F8E83", "name": "5", "rect": {"x": 534.5, "y": 962.5, "width": 1, "height": 268.953125}, "_class": "shapeGroup", "color": [0.847, 0.847, 0.847, 1], "label": 1}, {"id": "0439EE3A-E4D8-4BCB-8A8A-3A48BEDDB47D", "name": "May 17", "rect": {"x": 544, "y": 961, "width": 47, "height": 19}, "_class": "text", "color": [0.0, 0.0, 0.0, 0.0], "label": 1}, {"id": "AED5BB10-6770-4811-988B-40CA61302877", "name": "4", "rect": {"x": 653.5, "y": 962.5, "width": 1, "height": 268.953125}, "_class": "shapeGroup", "color": [0.847, 0.847, 0.847, 1], "label": 1}, {"id": "C5B48A01-DC1F-4BE8-9E05-694E13A11412", "name": "Jun 17", "rect": {"x": 663, "y": 961, "width": 42, "height": 19}, "_class": "text", "color": [0.0, 0.0, 0.0, 0.0], "label": 1}, {"id": "E1E84A95-4376-46BA-8D6F-BAC7BF65DD4D", "name": "3", "rect": {"x": 772.5, "y": 962.5, "width": 1, "height": 268.953125}, "_class": "shapeGroup", "color": [0.847, 0.847, 0.847, 1], "label": 1}, {"id": "2CFADA25-AD50-4E52-BE41-DD48A59BF3D3", "name": "Jul 17", "rect": {"x": 782, "y": 961, "width": 37, "height": 19}, "_class": "text", "color": [0.0, 0.0, 0.0, 0.0], "label": 1}, {"id": "F09B123C-B505-4AA7-A6CC-265E1189B57A", "name": "2", "rect": {"x": 891.5, "y": 962.5, "width": 1, "height": 268.953125}, "_class": "shapeGroup", "color": [0.847, 0.847, 0.847, 1], "label": 1}, {"id": "C3F470DA-5547-4C71-B289-B9C327916405", "name": "Aug 17", "rect": {"x": 901, "y": 961, "width": 45, "height": 19}, "_class": "text", "color": [0.0, 0.0, 0.0, 0.0], "label": 1}, {"id": "22964973-5CF7-44E0-81CB-719CB056151C", "name": "1", "rect": {"x": 1010.5, "y": 962.5, "width": 1, "height": 268.953125}, "_class": "shapeGroup", "color": [0.847, 0.847, 0.847, 1], "label": 1}, {"id": "60D5334D-0FAD-4A3F-915A-7061933DDEF9", "name": "Sep 17", "rect": {"x": 1020, "y": 961, "width": 43, "height": 19}, "_class": "text", "color": [0.0, 0.0, 0.0, 0.0], "label": 1}, {"id": "6EAC9071-C2FC-4DE2-B707-B8941EE8D551", "name": "Graph_Fill", "rect": {"x": -23.81816573936294, "y": 995.1835937500018, "width": 1163.920579978078, "height": 235.87168650664626}, "_class": "shapeGroup", "color": [0.847, 0.847, 0.847, 1], "label": 1}, {"id": "ED598CD2-D8F8-4CC3-8CA0-265874AAA789", "name": "Graph_Contur", "rect": {"x": -24.61942697938889, "y": 993.8698754434222, "width": 1165.00318782003, "height": 238.323006747916}, "_class": "shapeGroup", "color": [0.847, 0.847, 0.847, 1], "label": 1}, {"id": "42A00A33-26B5-4EB7-9E1D-F884F866DB08", "name": "Point_Bg 4", "rect": {"x": 360, "y": 1107, "width": 16, "height": 16}, "_class": "shapeGroup", "color": [0, 0.4666666666666668, 1, 1], "label": 1}, {"id": "52A76453-FBC8-475A-B148-5FBBD58A208D", "name": "Point_Bg 3", "rect": {"x": 74, "y": 1123, "width": 16, "height": 16}, "_class": "shapeGroup", "color": [0, 0.4666666666666668, 1, 1], "label": 1}, {"id": "49047851-A8F3-46DC-94D3-F151D45F5421", "name": "Point_Bg 2", "rect": {"x": 690, "y": 1120, "width": 16, "height": 16}, "_class": "shapeGroup", "color": [0, 0.4666666666666668, 1, 1], "label": 1}, {"id": "498C0963-07AB-44EB-980D-4E29916C318C", "name": "Point_Bg 1", "rect": {"x": 1002, "y": 1020, "width": 16, "height": 16}, "_class": "shapeGroup", "color": [0, 0.4666666666666668, 1, 1], "label": 1}, {"id": "FA7C230E-C961-42C6-9B21-B065D05A7375", "name": "Baseline", "rect": {"x": -25.07376602127124, "y": 1231.0670391061449, "width": 1165, "height": 1}, "_class": "shapeGroup", "color": [0.847, 0.847, 0.847, 1], "label": 1}, {"id": "FFFA69E5-FFDC-4B15-B6B5-F5927D425E16", "name": "Point 4", "rect": {"x": 78, "y": 1121, "width": 9, "height": 19}, "_class": "text", "color": [0.0, 0.0, 0.0, 0.0], "label": 1}, {"id": "2812522A-8061-4E44-9C1C-68A4BC73D266", "name": "Point 3", "rect": {"x": 364, "y": 1105, "width": 8, "height": 19}, "_class": "text", "color": [0.0, 0.0, 0.0, 0.0], "label": 1}, {"id": "9D8C71A8-8BC3-4686-99D1-6761D7239869", "name": "Point 2", "rect": {"x": 694, "y": 1118, "width": 9, "height": 19}, "_class": "text", "color": [0.0, 0.0, 0.0, 0.0], "label": 1}, {"id": "CB9980A3-E239-49AF-99D9-856B5E4462BA", "name": "Point 1", "rect": {"x": 1006, "y": 1018, "width": 10, "height": 19}, "_class": "text", "color": [0.0, 0.0, 0.0, 0.0], "label": 1}, {"id": "1FA26540-AFEF-41FF-B707-BFFA31E72A45", "name": "Troy May", "rect": {"x": 25, "y": 877, "width": 206, "height": 21}, "_class": "text", "color": [0.0, 0.0, 0.0, 0.0], "label": 1}, {"id": "67DCBFA4-C690-4B76-9CED-DCDF481BBAFE", "name": "Madagascar | Denmark Copy", "rect": {"x": 200, "y": 876, "width": 173, "height": 21}, "_class": "text", "color": [0.0, 0.0, 0.0, 0.0], "label": 1}, {"id": "3C6B12D9-B4C7-41ED-8145-A3F867B43978", "name": "divider", "rect": {"x": -394.25, "y": 855.75, "width": 1162.5, "height": 0.5}, "_class": "shapeGroup", "color": [0.847, 0.847, 0.847, 1], "label": 1}, {"id": "9A021C87-5051-4A88-9FE9-996417FF8BD8", "name": "Row_Bg Copy", "rect": {"x": -25, "y": 788, "width": 1164, "height": 67}, "_class": "shapeGroup", "color": [1, 1, 1, 1], "label": 1}, {"id": "AB6FDA5C-FC8F-45DC-8088-EB0F7F3BCD45", "name": "Brandon Osborne", "rect": {"x": 25, "y": 810, "width": 206, "height": 21}, "_class": "text", "color": [0.0, 0.0, 0.0, 0.0], "label": 1}, {"id": "3A6F7199-3E09-4017-BF83-B7F958CA00E3", "name": "Venezuela | Finland Copy", "rect": {"x": 200, "y": 809, "width": 173, "height": 21}, "_class": "text", "color": [0.0, 0.0, 0.0, 0.0], "label": 1}, {"id": "D8241B08-960D-4B57-8DE0-A67D4ED29F4B", "name": "Mike Gordon", "rect": {"x": 25, "y": 743, "width": 206, "height": 21}, "_class": "text", "color": [0.0, 0.0, 0.0, 0.0], "label": 1}, {"id": "2C10527C-6405-4004-80A1-BC9013C309B5", "name": "Djibouti | Norway Copy", "rect": {"x": 200, "y": 742, "width": 173, "height": 21}, "_class": "text", "color": [0.0, 0.0, 0.0, 0.0], "label": 1}, {"id": "31FB763C-0440-448C-82CB-A11292761CEC", "name": "divider", "rect": {"x": -394.25, "y": 788.75, "width": 1162.5, "height": 0.5}, "_class": "shapeGroup", "color": [0.847, 0.847, 0.847, 1], "label": 1}, {"id": "EF0FFC12-7C38-47D0-B98E-1437B71F7F62", "name": "Rectangle Copy", "rect": {"x": -25, "y": 654, "width": 1164, "height": 67}, "_class": "shapeGroup", "color": [1, 1, 1, 1], "label": 1}, {"id": "0929FB0C-9564-4571-8879-7C7B917BBD49", "name": "Jeffery Ortega", "rect": {"x": 25, "y": 676, "width": 206, "height": 21}, "_class": "text", "color": [0.0, 0.0, 0.0, 0.0], "label": 1}, {"id": "C74E6AA8-D7E3-4C20-9B48-0264638B70B4", "name": "Mayotte | Germany Copy", "rect": {"x": 200, "y": 675, "width": 173, "height": 21}, "_class": "text", "color": [0.0, 0.0, 0.0, 0.0], "label": 1}, {"id": "74697260-E8D4-4A2C-BD21-7DF0B6520920", "name": "divider", "rect": {"x": -394.25, "y": 721.75, "width": 1162.5, "height": 0.5}, "_class": "shapeGroup", "color": [0.847, 0.847, 0.847, 1], "label": 1}, {"id": "670482A4-853C-4ABD-B2F2-8AE56CA7FB74", "name": "Noah Wallace", "rect": {"x": 25, "y": 609, "width": 206, "height": 21}, "_class": "text", "color": [0.0, 0.0, 0.0, 0.0], "label": 1}, {"id": "1C1DD60E-6ACB-4FD8-8C9B-FFE5B749CCDA", "name": "Madagascar | Denmark", "rect": {"x": 200, "y": 608, "width": 173, "height": 21}, "_class": "text", "color": [0.0, 0.0, 0.0, 0.0], "label": 1}, {"id": "57097022-15D7-4798-A28C-7C480CAA741F", "name": "divider", "rect": {"x": -394.25, "y": 654.75, "width": 1162.5, "height": 0.5}, "_class": "shapeGroup", "color": [0.847, 0.847, 0.847, 1], "label": 1}, {"id": "6D8ACFEC-1EF9-488C-9E52-35DBEFF0277B", "name": "Row_Bg", "rect": {"x": -25, "y": 520, "width": 1164, "height": 67}, "_class": "shapeGroup", "color": [1, 1, 1, 1], "label": 1}, {"id": "1EF3C2AD-650A-4E75-9492-4D8FB5157CC9", "name": "Mason Thornton", "rect": {"x": 25, "y": 542, "width": 206, "height": 21}, "_class": "text", "color": [0.0, 0.0, 0.0, 0.0], "label": 1}, {"id": "C092C3EC-AE3A-423F-AEB7-140083FFFE3B", "name": "Venezuela | Finland", "rect": {"x": 200, "y": 541, "width": 173, "height": 21}, "_class": "text", "color": [0.0, 0.0, 0.0, 0.0], "label": 1}, {"id": "F0F788EB-67F9-4516-B728-6708A3EDAED0", "name": "divider", "rect": {"x": -394.25, "y": 587.75, "width": 1162.5, "height": 0.5}, "_class": "shapeGroup", "color": [0.847, 0.847, 0.847, 1], "label": 1}, {"id": "0255F25F-F699-4BE9-A0F6-43ADA2BD123E", "name": "Bessie Owens", "rect": {"x": 25, "y": 475, "width": 206, "height": 21}, "_class": "text", "color": [0.0, 0.0, 0.0, 0.0], "label": 1}, {"id": "6B12BB83-29A3-4637-AAE5-2787CB8AAB1D", "name": "Djibouti | Norway", "rect": {"x": 200, "y": 474, "width": 173, "height": 21}, "_class": "text", "color": [0.0, 0.0, 0.0, 0.0], "label": 1}, {"id": "B3D094C3-1830-47BA-9820-514E7EACE02B", "name": "divider", "rect": {"x": -394.25, "y": 519.75, "width": 1162.5, "height": 0.5}, "_class": "shapeGroup", "color": [0.847, 0.847, 0.847, 1], "label": 1}, {"id": "346F11EA-5A24-4851-AB05-884F65E7BF9D", "name": "Rectangle", "rect": {"x": -25, "y": 386, "width": 1164, "height": 67}, "_class": "shapeGroup", "color": [1, 1, 1, 1], "label": 1}, {"id": "AC0FBEED-FB8C-4688-AF9C-8ADF671ABEF0", "name": "Cole Hines", "rect": {"x": 25, "y": 408, "width": 206, "height": 21}, "_class": "text", "color": [0.0, 0.0, 0.0, 0.0], "label": 1}, {"id": "B618FA96-9D64-4DB6-B149-61BEBE6172CB", "name": "Mayotte | Germany", "rect": {"x": 200, "y": 407, "width": 173, "height": 21}, "_class": "text", "color": [0.0, 0.0, 0.0, 0.0], "label": 1}, {"id": "7E77664B-F3E4-4E02-9491-B0275674967F", "name": "divider", "rect": {"x": -394.25, "y": 452.75, "width": 1162.5, "height": 0.5}, "_class": "shapeGroup", "color": [0.847, 0.847, 0.847, 1], "label": 1}, {"id": "F8D3FF8C-B4E9-4B4F-90AB-E1FA01F3F35E", "name": "Henry Woods", "rect": {"x": 25, "y": 341, "width": 206, "height": 21}, "_class": "text", "color": [0.0, 0.0, 0.0, 0.0], "label": 1}, {"id": "E2F0D8BA-5AAE-4167-9C0C-007FCFCCD7C9", "name": "Georgia | France", "rect": {"x": 200, "y": 340, "width": 173, "height": 21}, "_class": "text", "color": [0.0, 0.0, 0.0, 0.0], "label": 1}, {"id": "B61AEC6F-2972-4A98-870B-D1431DE37242", "name": "divider", "rect": {"x": -394.25, "y": 385.75, "width": 1162.5, "height": 0.5}, "_class": "shapeGroup", "color": [0.847, 0.847, 0.847, 1], "label": 1}, {"id": "2C636169-6BDE-4FB5-B499-7D7EBA515AF5", "name": "Rectangle", "rect": {"x": -25, "y": 252, "width": 1164, "height": 67}, "_class": "shapeGroup", "color": [1, 1, 1, 1], "label": 1}, {"id": "ABF3260C-77EF-41E0-8185-E5AFB7971658", "name": "Logan Greer", "rect": {"x": 25, "y": 274, "width": 206, "height": 21}, "_class": "text", "color": [0.0, 0.0, 0.0, 0.0], "label": 1}, {"id": "1EF50FA1-2BA1-43DA-B233-E77B24F40BBD", "name": "Cook Islands | Nicar", "rect": {"x": 200, "y": 273, "width": 173, "height": 21}, "_class": "text", "color": [0.0, 0.0, 0.0, 0.0], "label": 1}, {"id": "E2E692FA-1BF6-48A3-80CE-DD49E263D437", "name": "divider", "rect": {"x": -24.25, "y": 318.75, "width": 1162.5, "height": 0.5}, "_class": "shapeGroup", "color": [0.847, 0.847, 0.847, 1], "label": 1}, {"id": "7456E287-6E23-4A8B-8D08-BD910CAF878C", "name": "Jimmy Lowe", "rect": {"x": 25, "y": 207, "width": 206, "height": 21}, "_class": "text", "color": [0.0, 0.0, 0.0, 0.0], "label": 1}, {"id": "43EF70BA-E6C8-4B84-AA21-DE4E43046EC5", "name": "Paraguay | United St", "rect": {"x": 200, "y": 206, "width": 173, "height": 21}, "_class": "text", "color": [0.0, 0.0, 0.0, 0.0], "label": 1}, {"id": "893FFC98-9D36-46EB-83CA-B5F48CBAB154", "name": "divider", "rect": {"x": -24.25, "y": 251.75, "width": 1162.5, "height": 0.5}, "_class": "shapeGroup", "color": [0.847, 0.847, 0.847, 1], "label": 1}, {"id": "D1191AC0-A6B9-433C-AF07-9B66A8F2A179", "name": "Rectangle", "rect": {"x": -25, "y": 118, "width": 1164, "height": 67}, "_class": "shapeGroup", "color": [1, 1, 1, 1], "label": 1}, {"id": "0760C3F5-A696-4A54-AB30-65BE358F6CD2", "name": "Line", "rect": {"x": -24.25, "y": 184.75, "width": 1162.5, "height": 0.5}, "_class": "shapeGroup", "color": [0.847, 0.847, 0.847, 1], "label": 1}, {"id": "FE2711FD-64AA-4DF4-8F5D-7AB00FC9D786", "name": "Tillie Delgado", "rect": {"x": 25, "y": 140, "width": 130, "height": 21}, "_class": "text", "color": [0.0, 0.0, 0.0, 0.0], "label": 1}, {"id": "000861DC-BE5F-473E-9A64-5025FF5F0708", "name": "Timor-Leste | Italy", "rect": {"x": 200, "y": 139, "width": 173, "height": 21}, "_class": "text", "color": [0.0, 0.0, 0.0, 0.0], "label": 1}, {"id": "5EF3A770-F287-45D3-A70B-1169AC0BFB19", "name": "ic_Arrow to sort", "rect": {"x": 98.83532934131745, "y": 97, "width": 14, "height": 14}, "_class": "bitmap", "color": [0.8, 0.8117647058823529, 0.8313725490196079, 1], "label": 1}, {"id": "D3ED0754-4FC7-4D12-A08F-CD7DF4C024D7", "name": "ic_Arrow to sort", "rect": {"x": 550.8353293413174, "y": 97, "width": 14, "height": 14}, "_class": "bitmap", "color": [0.8, 0.8117647058823529, 0.8313725490196079, 1], "label": 1}, {"id": "D46BF985-4792-4497-8D4E-66E679FA827E", "name": "ic_Arrow to sort", "rect": {"x": 735.8353293413174, "y": 97, "width": 14, "height": 14}, "_class": "bitmap", "color": [0.8, 0.8117647058823529, 0.8313725490196079, 1], "label": 1}, {"id": "748BCDEE-BF1E-4BE7-8C12-8487EBF8DADE", "name": "ic_Arrow to sort", "rect": {"x": 278.83532934131745, "y": 97, "width": 14, "height": 14}, "_class": "bitmap", "color": [0.8, 0.8117647058823529, 0.8313725490196079, 1], "label": 1}, {"id": "C585E603-BF0B-425A-AD3F-EB587A4B2499", "name": "ic_Arrow to sort", "rect": {"x": 938.8353293413174, "y": 97, "width": 14, "height": 14}, "_class": "bitmap", "color": [0.8, 0.8117647058823529, 0.8313725490196079, 1], "label": 1}, {"id": "FD7A0CE1-CAD0-4195-88E0-192F76E43B64", "name": "ic_Arrow to sort", "rect": {"x": 1061.8353293413174, "y": 97, "width": 14, "height": 14}, "_class": "bitmap", "color": [0.8, 0.8117647058823529, 0.8313725490196079, 1], "label": 1}, {"id": "0E4A6292-52C4-4C3E-8092-CBB4E21DDA58", "name": "Column name 6", "rect": {"x": 991.0732575529937, "y": 96.94604500965215, "width": 112.68279389067948, "height": 12}, "_class": "text", "color": [0.0, 0.0, 0.0, 0.0], "label": 1}, {"id": "810B8DB4-E9DA-49B8-8897-18A66F79EA87", "name": "Column name 5", "rect": {"x": 848.0732575529937, "y": 96.94604500965215, "width": 112.68279389067948, "height": 12}, "_class": "text", "color": [0.0, 0.0, 0.0, 0.0], "label": 1}, {"id": "419A2357-6348-4057-A3F3-7422587CB8A3", "name": "Column name 4", "rect": {"x": 198.45005019394648, "y": 96.95118358016225, "width": 77.58520849267961, "height": 12}, "_class": "text", "color": [0.0, 0.0, 0.0, 0.0], "label": 1}, {"id": "5CCF6D46-2480-44BB-B16D-B71361C7F4A6", "name": "Column name 3", "rect": {"x": 677.1085162396203, "y": 96.94604500965215, "width": 60.8914837603802, "height": 12}, "_class": "text", "color": [0.0, 0.0, 0.0, 0.0], "label": 1}, {"id": "7E1D786A-E68F-4E0B-9EE1-FD6164A5D3A4", "name": "Column name 2", "rect": {"x": 480, "y": 96.94604500965215, "width": 70, "height": 12}, "_class": "text", "color": [0.0, 0.0, 0.0, 0.0], "label": 1}, {"id": "30BB9BD6-526D-4981-94D9-90B2D4EB1596", "name": "Column name 1", "rect": {"x": 14.670766977163112, "y": 96.94604500965215, "width": 89, "height": 12}, "_class": "text", "color": [0.0, 0.0, 0.0, 0.0], "label": 1}, {"id": "310810BA-FA22-4DB9-B0D9-9C90DF612438", "name": "Head background", "rect": {"x": 0, "y": 0, "width": 375, "height": 64}, "_class": "shapeGroup", "color": [1, 1, 1, 1], "label": 1}, {"id": "DBC77E2D-9236-4E18-960C-46EF92F9F758", "name": "Hamburger", "rect": {"x": 324, "y": 16, "width": 31, "height": 31}, "_class": "bitmap", "color": [0.726769846214557, 0.7684962337312627, 0.8232621173469388, 1], "label": 1}, {"id": "EEE135AF-86C8-46B1-A272-55C0E1AAABBD", "name": "Line", "rect": {"x": -292.25, "y": 62.75, "width": 958.6064694122178, "height": 0.5}, "_class": "shapeGroup", "color": [0.847, 0.847, 0.847, 1], "label": 1}, {"id": "B8853CB9-A2CF-4361-AED4-5F0A9057568A", "name": "Oval 4", "rect": {"x": 16, "y": 14.799999952316284, "width": 32.399999141693115, "height": 32.39999914169312}, "_class": "shapeGroup", "color": [0, 0.4666666666666668, 1, 1], "label": 1}, {"id": "C5CEB76B-23BD-496B-AF1D-0B29AEC3DE08", "name": ".", "rect": {"x": 28.59999966621399, "y": 13, "width": 9, "height": 36}, "_class": "text", "color": [0.0, 0.0, 0.0, 0.0], "label": 1}], "width": 375, "height": 1374, "layer_width": 64, "layer_height": 64}