{"layers": [{"id": "7FBCDFC2-EC2C-4551-ADD1-FDDF2901B7AB", "name": "Divider", "rect": {"x": 19, "y": 208, "width": 356, "height": 1}, "_class": "shapeGroup", "color": [0.9450980392156862, 0.9450980392156862, 0.9450980392156862, 1], "label": 0}, {"id": "BF826EC4-8482-4511-82C4-05A9389BAA12", "name": "Userpic", "rect": {"x": 20, "y": 144, "width": 50, "height": 50}, "_class": "shapeGroup", "color": [0.1333333333333333, 0.1372549019607844, 0.1568627450980392, 1], "label": 1}, {"id": "CD0F70D7-EDED-42A6-84B0-FFCE110260BC", "name": "Dropbox is doing it,", "rect": {"x": 85, "y": 173, "width": 280, "height": 22}, "_class": "text", "color": [0.0, 0.0, 0.0, 0.0], "label": 1}, {"id": "FAA738AB-8736-4389-9C11-A3CE4EEB51F9", "name": "8:24 AM", "rect": {"x": 302, "y": 150, "width": 51, "height": 19}, "_class": "text", "color": [0.0, 0.0, 0.0, 0.0], "label": 1}, {"id": "4DFEBCD2-DC7F-46FF-9380-0DF25313EE62", "name": "Isabel Walsh", "rect": {"x": 85, "y": 145, "width": 110, "height": 27}, "_class": "text", "color": [0.0, 0.0, 0.0, 0.0], "label": 1}, {"id": "C6A812DC-6598-4A34-BD40-19D76E3F3E54", "name": "Bages/Red BG", "rect": {"x": 196, "y": 146, "width": 30, "height": 30}, "_class": "symbolInstance", "color": [0.0, 0.0, 0.0, 0.0], "label": 1}, {"id": "6B6EB95E-BA22-40DB-925F-55A45F3DD14B", "name": "Divider", "rect": {"x": 19, "y": 288, "width": 356, "height": 1}, "_class": "shapeGroup", "color": [0.9450980392156862, 0.9450980392156862, 0.9450980392156862, 1], "label": 1}, {"id": "C68F3AA7-C5C8-45A5-958D-96E59F89B51C", "name": "Userpic", "rect": {"x": 20, "y": 224, "width": 50, "height": 50}, "_class": "shapeGroup", "color": [0.1333333333333333, 0.1372549019607844, 0.1568627450980392, 1], "label": 1}, {"id": "E1726E00-B32F-4518-96C9-30D9E8CEEB1A", "name": "Nice and clean", "rect": {"x": 85, "y": 253, "width": 258, "height": 22}, "_class": "text", "color": [0.0, 0.0, 0.0, 0.0], "label": 1}, {"id": "BFDDD919-6377-47ED-94C7-024C3F48F1E8", "name": "7:32 AM", "rect": {"x": 302, "y": 230, "width": 51, "height": 19}, "_class": "text", "color": [0.0, 0.0, 0.0, 0.0], "label": 1}, {"id": "EEF3198E-B0E6-46A4-95A5-EA70AB9CBAAE", "name": "Sara Glover", "rect": {"x": 85, "y": 225, "width": 101, "height": 27}, "_class": "text", "color": [0.0, 0.0, 0.0, 0.0], "label": 1}, {"id": "2A989A8B-2479-424D-9138-0A922348E2BC", "name": "Bages/Red BG", "rect": {"x": 187, "y": 226, "width": 30, "height": 30}, "_class": "symbolInstance", "color": [0.0, 0.0, 0.0, 0.0], "label": 1}, {"id": "ABA36A60-222D-40C0-85AF-67D33DB6B8B3", "name": "Divider", "rect": {"x": 19, "y": 368, "width": 356, "height": 1}, "_class": "shapeGroup", "color": [0.9450980392156862, 0.9450980392156862, 0.9450980392156862, 1], "label": 1}, {"id": "4DCE435E-3803-43CB-AE4C-E52297C3F840", "name": "Userpic", "rect": {"x": 20, "y": 304, "width": 50, "height": 50}, "_class": "shapeGroup", "color": [0.1333333333333333, 0.1372549019607844, 0.1568627450980392, 1], "label": 1}, {"id": "06F6A0CF-4B67-4444-9F5A-300ED2F3057F", "name": "Brandon: Inbox will", "rect": {"x": 85, "y": 333, "width": 280, "height": 22}, "_class": "text", "color": [0.0, 0.0, 0.0, 0.0], "label": 1}, {"id": "6AAD20E1-AB38-4026-B972-3118624FE26B", "name": "7:18 AM", "rect": {"x": 302, "y": 310, "width": 51, "height": 19}, "_class": "text", "color": [0.0, 0.0, 0.0, 0.0], "label": 1}, {"id": "8C7CBA37-5D05-47A8-BD44-23FB93B6BEFF", "name": "How I met your Pro..", "rect": {"x": 85, "y": 305, "width": 180, "height": 27}, "_class": "text", "color": [0.0, 0.0, 0.0, 0.0], "label": 1}, {"id": "D5E5503B-46BE-40F9-BA7A-E3FC74AF9BB7", "name": "Bages/Red BG", "rect": {"x": 263, "y": 306, "width": 30, "height": 30}, "_class": "symbolInstance", "color": [0.0, 0.0, 0.0, 0.0], "label": 1}, {"id": "19E26108-0F95-4FAA-BB0D-6E5A35538679", "name": "Divider", "rect": {"x": 19, "y": 448, "width": 356, "height": 1}, "_class": "shapeGroup", "color": [0.9450980392156862, 0.9450980392156862, 0.9450980392156862, 1], "label": 1}, {"id": "F21CDEC3-872C-4797-92CF-12C0E2BF5FAF", "name": "Userpic", "rect": {"x": 20, "y": 384, "width": 50, "height": 50}, "_class": "shapeGroup", "color": [0.1333333333333333, 0.1372549019607844, 0.1568627450980392, 1], "label": 1}, {"id": "69EA0CAD-22CD-4D2E-9C50-D4B3E80C2BF1", "name": "Denis: \ud83d\ude2e", "rect": {"x": 85, "y": 409, "width": 280, "height": 26}, "_class": "text", "color": [0.0, 0.0, 0.0, 0.0], "label": 1}, {"id": "72DA2FC0-8F41-45E6-A46C-ED2D1B845C12", "name": "11:12 PM", "rect": {"x": 296, "y": 390, "width": 57, "height": 19}, "_class": "text", "color": [0.0, 0.0, 0.0, 0.0], "label": 1}, {"id": "E42A557E-1B06-43B7-AFB0-2B1E0625191E", "name": "Dribbble", "rect": {"x": 85, "y": 385, "width": 74, "height": 27}, "_class": "text", "color": [0.0, 0.0, 0.0, 0.0], "label": 1}, {"id": "D902A5C8-06D4-4792-B7F6-4B871FBDF8B5", "name": "Bages/Red BG", "rect": {"x": 163, "y": 386, "width": 37, "height": 30}, "_class": "symbolInstance", "color": [0.0, 0.0, 0.0, 0.0], "label": 1}, {"id": "A9955C71-DCD6-41E9-A153-113F414810D1", "name": "Divider", "rect": {"x": 19, "y": 528, "width": 356, "height": 1}, "_class": "shapeGroup", "color": [0.9450980392156862, 0.9450980392156862, 0.9450980392156862, 1], "label": 1}, {"id": "98CAAEEF-DB13-4F04-9BD2-4DC942A35201", "name": "Userpic", "rect": {"x": 20, "y": 464, "width": 50, "height": 50}, "_class": "shapeGroup", "color": [0.1333333333333333, 0.1372549019607844, 0.1568627450980392, 1], "label": 1}, {"id": "5D5AEC51-2F02-4618-8DFE-A97A35E3E094", "name": "Hell yeah!", "rect": {"x": 85, "y": 493, "width": 258, "height": 22}, "_class": "text", "color": [0.0, 0.0, 0.0, 0.0], "label": 1}, {"id": "BD17173F-E369-4068-B025-D2DAABC67DDA", "name": "12:21 PM", "rect": {"x": 296, "y": 470, "width": 57, "height": 19}, "_class": "text", "color": [0.0, 0.0, 0.0, 0.0], "label": 1}, {"id": "0C0E5F0E-291D-48B9-A40C-D879BAF28283", "name": "Adrian Bell", "rect": {"x": 85, "y": 465, "width": 95, "height": 27}, "_class": "text", "color": [0.0, 0.0, 0.0, 0.0], "label": 1}, {"id": "34559BCE-7BA0-4B7D-89A1-C6DD49A22E51", "name": "Divider", "rect": {"x": 19, "y": 608, "width": 356, "height": 1}, "_class": "shapeGroup", "color": [0.9450980392156862, 0.9450980392156862, 0.9450980392156862, 1], "label": 1}, {"id": "0B4E9CAD-C3F1-4E08-973C-19E888B9810F", "name": "Userpic", "rect": {"x": 20, "y": 544, "width": 50, "height": 50}, "_class": "shapeGroup", "color": [0.1333333333333333, 0.1372549019607844, 0.1568627450980392, 1], "label": 1}, {"id": "64FB74AF-BEE0-4D22-B4EF-046D6ED9E2CF", "name": "Paul: Awesome bro! P", "rect": {"x": 85, "y": 573, "width": 280, "height": 22}, "_class": "text", "color": [0.0, 0.0, 0.0, 0.0], "label": 1}, {"id": "4FA88263-DFEE-43E8-B402-BF5B3EFAE158", "name": "Yesterday", "rect": {"x": 296, "y": 550, "width": 58, "height": 19}, "_class": "text", "color": [0.0, 0.0, 0.0, 0.0], "label": 1}, {"id": "ABD7FFBD-3513-4730-8160-82844D218423", "name": "Best Music Channel", "rect": {"x": 85, "y": 545, "width": 169, "height": 27}, "_class": "text", "color": [0.0, 0.0, 0.0, 0.0], "label": 1}, {"id": "50D48872-7816-46EC-8303-56E2BD3A9B54", "name": "Divider", "rect": {"x": 19, "y": 688, "width": 346, "height": 1}, "_class": "shapeGroup", "color": [0.9450980392156862, 0.9450980392156862, 0.9450980392156862, 1], "label": 1}, {"id": "8C7D0EAA-75A5-4A2C-8E92-9B6BAADC1925", "name": "Userpic", "rect": {"x": 20, "y": 624, "width": 50, "height": 50}, "_class": "shapeGroup", "color": [0.1333333333333333, 0.1372549019607844, 0.1568627450980392, 1], "label": 1}, {"id": "B3399919-DD83-4121-A2F7-5B158431349B", "name": "Marc Brunet: Noooooo", "rect": {"x": 85, "y": 653, "width": 280, "height": 22}, "_class": "text", "color": [0.0, 0.0, 0.0, 0.0], "label": 1}, {"id": "70AC7850-733B-4E00-8ABE-7DA3C530AB98", "name": "Yesterday", "rect": {"x": 296, "y": 630, "width": 58, "height": 19}, "_class": "text", "color": [0.0, 0.0, 0.0, 0.0], "label": 1}, {"id": "DED92980-A75C-4E17-9464-7569BEC06159", "name": "HyperX", "rect": {"x": 85, "y": 625, "width": 66, "height": 27}, "_class": "text", "color": [0.0, 0.0, 0.0, 0.0], "label": 1}, {"id": "24A2C90E-7FBE-4234-8505-05BEAC0AFA6F", "name": "Rectangle 3", "rect": {"x": 343, "y": 41, "width": 2, "height": 20}, "_class": "rectangle", "color": [0.0, 0.0, 0.0, 0.0], "label": 1}, {"id": "895AE53F-7DD7-4DC5-AFCB-4D3A7873D2C3", "name": "Rectangle 3", "rect": {"x": 334, "y": 50, "width": 20, "height": 2}, "_class": "rectangle", "color": [0.0, 0.0, 0.0, 0.0], "label": 1}, {"id": "05589AA7-8562-43A1-856C-A152BF7B1524", "name": "Input Field", "rect": {"x": 47, "y": 83, "width": 306, "height": 40}, "_class": "symbolInstance", "color": [0.0, 0.0, 0.0, 0.0], "label": 1}, {"id": "B5A7267D-1DB2-4B0B-BEAE-867743BA9A0F", "name": "Sparks", "rect": {"x": 48, "y": 33, "width": 79, "height": 35}, "_class": "text", "color": [0.0, 0.0, 0.0, 0.0], "label": 1}, {"id": "1E6609AF-71B1-4FDF-8999-B87163E8F438", "name": "Rectangle 4", "rect": {"x": 20, "y": 43, "width": 18, "height": 2}, "_class": "rectangle", "color": [0.0, 0.0, 0.0, 0.0], "label": 1}, {"id": "27135C19-8F7C-40A8-83B0-084734018734", "name": "Rectangle 4", "rect": {"x": 20, "y": 50, "width": 18, "height": 2}, "_class": "rectangle", "color": [0.0, 0.0, 0.0, 0.0], "label": 1}, {"id": "FFB7B981-8142-41C5-A96A-4D4A3616EA97", "name": "Rectangle 4", "rect": {"x": 20, "y": 57, "width": 18, "height": 2}, "_class": "rectangle", "color": [0.0, 0.0, 0.0, 0.0], "label": 1}, {"id": "B7C2421F-395A-4BA7-BA6E-EC6DF614F95D", "name": "Status Bar", "rect": {"x": 6, "y": 3.5, "width": 363.5, "height": 14.8203125}, "_class": "symbolInstance", "color": [0.0, 0.0, 0.0, 0.0], "label": 1}], "width": 375, "height": 667, "layer_width": 64, "layer_height": 64}