{"layers": [{"id": "6A952A87-8A6B-4E0C-BDBE-F186C3FDD329", "name": "Background", "rect": {"x": 0, "y": 0, "width": 375, "height": 812}, "_class": "shapeGroup", "color": [0, 0.4549019607843137, 0.9098039215686274, 1], "label": 0}, {"id": "FBDB6CE4-3F3B-43C0-86FA-86CB9F619A27", "name": "Rectangle", "rect": {"x": 0, "y": 715, "width": 375, "height": 97}, "_class": "shapeGroup", "color": [0.003921568627450959, 0.4588235294117646, 0.9019607843137255, 1], "label": 1}, {"id": "6F550334-92D8-464E-9857-92575EE8E105", "name": "Button", "rect": {"x": 20, "y": 735, "width": 335, "height": 48}, "_class": "shapeGroup", "color": [1, 1, 1, 1], "label": 1}, {"id": "712A7AFB-F80B-4AAC-B75B-EC9CBB70049C", "name": "Confirm Address", "rect": {"x": 107.5, "y": 752, "width": 160, "height": 15}, "_class": "text", "color": [0.0, 0.0, 0.0, 0.0], "label": 1}, {"id": "7D69E35B-31EB-482A-A092-B0BCE0D62739", "name": "Home indicator", "rect": {"x": 123, "y": 801, "width": 134, "height": 5}, "_class": "shapeGroup", "color": [1, 1, 1, 1], "label": 1}, {"id": "56AB40A0-2A81-4ED2-8E87-1FF838FAF1DB", "name": "First Line of Addres", "rect": {"x": 93, "y": 232, "width": 189, "height": 15}, "_class": "text", "color": [0.0, 0.0, 0.0, 0.0], "label": 1}, {"id": "4295CFF5-46E8-49BD-A2FA-6EB2580B616D", "name": "Line", "rect": {"x": 20, "y": 276, "width": 336, "height": 1}, "_class": "shapeGroup", "color": [0.847, 0.847, 0.847, 1], "label": 1}, {"id": "08507F2B-824D-435A-879D-0E6BADDD5B24", "name": "Line", "rect": {"x": 20, "y": 350, "width": 336, "height": 1}, "_class": "shapeGroup", "color": [0.847, 0.847, 0.847, 1], "label": 1}, {"id": "A2296673-2EF4-488D-AD6E-C99438AC1A68", "name": "Line", "rect": {"x": 20, "y": 424, "width": 336, "height": 1}, "_class": "shapeGroup", "color": [0.847, 0.847, 0.847, 1], "label": 1}, {"id": "1FE6A010-16CB-4919-9985-EEF4547F4170", "name": "Line", "rect": {"x": 20, "y": 498, "width": 336, "height": 1}, "_class": "shapeGroup", "color": [0.847, 0.847, 0.847, 1], "label": 1}, {"id": "10FE85D9-B131-4A91-A0C1-518FB543F782", "name": "Second Line of Addre", "rect": {"x": 79, "y": 306, "width": 216, "height": 15}, "_class": "text", "color": [0.0, 0.0, 0.0, 0.0], "label": 1}, {"id": "5C80A998-9F67-45EE-8230-9D13CF50BCE3", "name": "Postal Code", "rect": {"x": 132, "y": 380, "width": 110, "height": 15}, "_class": "text", "color": [0.0, 0.0, 0.0, 0.0], "label": 1}, {"id": "EF626F63-2DDE-4FE6-90DF-4D1CAFA8B711", "name": "City", "rect": {"x": 168.5, "y": 454, "width": 37, "height": 17}, "_class": "text", "color": [0.0, 0.0, 0.0, 0.0], "label": 1}, {"id": "99421BA1-050F-4EA6-B573-644AEEC2B9AB", "name": "Blur", "rect": {"x": 0, "y": 0, "width": 375, "height": 103}, "_class": "shapeGroup", "color": [0.1137254901960784, 0.1529411764705882, 0.1921568627450981, 1], "label": 1}, {"id": "94EBD8C5-AC87-4D36-925C-7A6328DB4023", "name": "Chevron_Right", "rect": {"x": 20.00939822068358, "y": 60.00008298755186, "width": 11.003796800063355, "height": 19.985228215767634}, "_class": "shapeGroup", "color": [0.003921568627450959, 0.4588235294117646, 0.9019607843137255, 1], "label": 1}, {"id": "E2871799-ACD8-4170-BB23-E1A709A480C9", "name": "Background", "rect": {"x": 0, "y": 103, "width": 375, "height": 80}, "_class": "shapeGroup", "color": [0.1137254901960784, 0.1529411764705882, 0.1921568627450981, 1], "label": 1}, {"id": "449947C6-43A4-444D-87E4-DB62BB410D9F", "name": "Registered Address", "rect": {"x": 89.5, "y": 128, "width": 197, "height": 27}, "_class": "text", "color": [0.0, 0.0, 0.0, 0.0], "label": 1}, {"id": "44D991D5-2EA8-49F2-AF60-B1E4CE959D3F", "name": "Progress", "rect": {"x": 0, "y": 102.99999999999999, "width": 375, "height": 1.0000000000000284}, "_class": "shapeGroup", "color": [1, 1, 1, 1], "label": 1}, {"id": "A1D2060A-3CD4-46BB-8890-6FCBA8EBE117", "name": "Rectangle 2", "rect": {"x": 0, "y": 103, "width": 216, "height": 1}, "_class": "shapeGroup", "color": [1, 1, 1, 1], "label": 1}, {"id": "D9EDA763-E8D9-4761-9596-8BBD2EB1D6F9", "name": "Border", "rect": {"x": 336, "y": 17.33333333333337, "width": 22, "height": 11.333333333333332}, "_class": "shapeGroup", "color": [0.0, 0.0, 0.0, 0.0], "label": 1}, {"id": "170353CF-B81A-4241-BDE6-3D6CC475AA5A", "name": "Cap", "rect": {"x": 359, "y": 21, "width": 1.3280380056075956, "height": 4}, "_class": "shapeGroup", "color": [0.1254901960784314, 0.2549019607843138, 0.3803921568627451, 1], "label": 1}, {"id": "BA1AF1F6-B415-4F0F-B2ED-C33CBC6F4871", "name": "Capacity", "rect": {"x": 338, "y": 19.33333333333337, "width": 18, "height": 7.333333333333332}, "_class": "shapeGroup", "color": [0.1254901960784314, 0.2549019607843138, 0.3803921568627451, 1], "label": 1}, {"id": "5818051D-ED6F-4938-9AAF-B1ED3DEA6224", "name": "Wifi-path", "rect": {"x": 315.6937206970724, "y": 17.330672704032505, "width": 15.272388453644453, "height": 4.743237397693161}, "_class": "shapePath", "color": [0.0, 0.0, 0.0, 0.0], "label": 1}, {"id": "428FF25E-1D6A-46F0-8B5D-5444C2EB860B", "name": "Wifi-path", "rect": {"x": 318.3569945543095, "y": 21.12471325332229, "width": 9.949041387462785, "height": 3.6339809392895184}, "_class": "shapePath", "color": [0.0, 0.0, 0.0, 0.0], "label": 1}, {"id": "67018E8C-5655-48C8-9F1E-099A4212BC48", "name": "Wifi-path", "rect": {"x": 321.0170997074347, "y": 24.92183711323497, "width": 4.626293640210861, "height": 3.3744071970963674}, "_class": "shapePath", "color": [0.0, 0.0, 0.0, 0.0], "label": 1}, {"id": "B652F89B-307D-4DC5-BD0E-123DF63E183F", "name": "Cellular_Connection-path", "rect": {"x": 293.66666666666606, "y": 24.3333333333333, "width": 3, "height": 4}, "_class": "shapePath", "color": [0.0, 0.0, 0.0, 0.0], "label": 1}, {"id": "577BEE12-240A-4A4F-A9DB-5F62183EE472", "name": "Cellular_Connection-path", "rect": {"x": 298.3333333333321, "y": 22.3333333333333, "width": 3, "height": 6}, "_class": "shapePath", "color": [0.0, 0.0, 0.0, 0.0], "label": 1}, {"id": "1EED9BBB-D183-4680-9065-465940C91001", "name": "Cellular_Connection-path", "rect": {"x": 303, "y": 19.999999999999964, "width": 3, "height": 8.333333333333332}, "_class": "shapePath", "color": [0.0, 0.0, 0.0, 0.0], "label": 1}, {"id": "FDC3E3CE-3D11-4E54-BD23-A973E4267DA4", "name": "Cellular_Connection-path", "rect": {"x": 307.66666666666606, "y": 17.66666666666663, "width": 3, "height": 10.666666666666671}, "_class": "shapePath", "color": [0.0, 0.0, 0.0, 0.0], "label": 1}, {"id": "26966E9F-BFBC-4FC2-AE76-69AA333177C6", "name": "Path", "rect": {"x": 35.28132812678814, "y": 19.9033203125, "width": 7.1708984375, "height": 10.322265625}, "_class": "shapePath", "color": [0.0, 0.0, 0.0, 0.0], "label": 1}, {"id": "EE53A1FC-1E48-4D13-97CA-57D0D0B25DAB", "name": "Path", "rect": {"x": 36.52546875178814, "y": 20.9833984375, "width": 4.45703125, "height": 4.552734375}, "_class": "shapePath", "color": [0.0, 0.0, 0.0, 0.0], "label": 1}, {"id": "C373A8DD-8AB1-4F5D-877D-CFD017672BC1", "name": "Path", "rect": {"x": 44.08628906309605, "y": 27.0947265625, "width": 1.77734375, "height": 1.77734375}, "_class": "shapePath", "color": [0.0, 0.0, 0.0, 0.0], "label": 1}, {"id": "7FAB2414-E186-4F8A-938C-C332452FE62B", "name": "Path", "rect": {"x": 44.08628906309605, "y": 21.837890625, "width": 1.77734375, "height": 1.77734375}, "_class": "shapePath", "color": [0.0, 0.0, 0.0, 0.0], "label": 1}, {"id": "FADF0A8F-0E01-49FA-8429-04E284C27AB2", "name": "Path", "rect": {"x": 47.42249999940395, "y": 20.1357421875, "width": 7.41015625, "height": 9.8642578125}, "_class": "shapePath", "color": [0.0, 0.0, 0.0, 0.0], "label": 1}, {"id": "3D94E06B-6F7F-4B0C-90C2-B14F11405133", "name": "Path", "rect": {"x": 48.68031249940395, "y": 21.27734375, "width": 3.5546875, "height": 5.5849609375}, "_class": "shapePath", "color": [0.0, 0.0, 0.0, 0.0], "label": 1}, {"id": "AF85A18E-FB3D-4A3D-9142-27D804FE4245", "name": "Path", "rect": {"x": 56.04289062321186, "y": 20.1357421875, "width": 3.8486328125, "height": 9.8642578125}, "_class": "shapePath", "color": [0.0, 0.0, 0.0, 0.0], "label": 1}, {"id": "4DC53DFE-AA01-4F64-BB4C-B98987B15622", "name": "Shape", "rect": {"x": 335.0008461538455, "y": 60.30753846153846, "width": 19.691538461538585, "height": 19.55492307692308}, "_class": "shapeGroup", "color": [1, 1, 1, 1], "label": 1}, {"id": "AB06D621-E9F1-47FE-ABF7-87CD3276385C", "name": "Personal Details", "rect": {"x": 73, "y": 56, "width": 230, "height": 26}, "_class": "text", "color": [0.847, 0.847, 0.847, 1], "label": 1}], "width": 375, "height": 812, "layer_width": 64, "layer_height": 64}