{"layers": [{"id": "0B9DD002-00A6-4FF7-9C7C-699FD3C91DAD", "name": "heloise_toy@gmail.co", "rect": {"x": 101, "y": 50, "width": 165, "height": 60}, "_class": "text", "color": [0.847, 0.847, 0.847, 1], "label": 0}, {"id": "60B7FE8C-6CB9-416F-AC03-07376A0FB088", "name": "Base", "rect": {"x": 207, "y": 144, "width": 198, "height": 231}, "_class": "shapeGroup", "color": [1, 1, 1, 1], "label": 1}, {"id": "0D32FEE5-236A-4FCE-87C9-74E9703AB13C", "name": "Heart", "rect": {"x": 298.5, "y": 232.5, "width": 15, "height": 13.991525423728802}, "_class": "shapeGroup", "color": [0.0, 0.0, 0.0, 0.0], "label": 1}, {"id": "7221A980-8944-4C8A-B79D-8261A61AFF3A", "name": "Notifications", "rect": {"x": 268, "y": 268, "width": 77, "height": 18}, "_class": "text", "color": [0.847, 0.847, 0.847, 1], "label": 1}, {"id": "5AE390F0-51EB-4A2D-A677-D5F0EFAC205A", "name": "Base", "rect": {"x": -31, "y": 144, "width": 198, "height": 231}, "_class": "shapeGroup", "color": [1, 1, 1, 1], "label": 1}, {"id": "69B1DAE0-2D32-4F4B-BB43-096D487B29E3", "name": "Stroke 17", "rect": {"x": 60.5, "y": 232.5, "width": 12, "height": 11.992829204693606}, "_class": "shapeGroup", "color": [0.0, 0.0, 0.0, 0.0], "label": 1}, {"id": "CE3C53C0-AA5F-475D-9B0C-C367CA4D52AB", "name": "Stroke 19", "rect": {"x": 70.49999999983311, "y": 242.49348109500903, "width": 5.0000000003337846, "height": 4.99739243840429}, "_class": "shapeGroup", "color": [0.0, 0.0, 0.0, 0.0], "label": 1}, {"id": "8670C157-47C7-470F-BDF5-ABC52FE7D374", "name": "Search", "rect": {"x": 47, "y": 268, "width": 42, "height": 18}, "_class": "text", "color": [0.847, 0.847, 0.847, 1], "label": 1}, {"id": "D17FF7B3-EF11-4248-B32E-F08AEA9C0E94", "name": "Base", "rect": {"x": 207, "y": 297, "width": 198, "height": 231}, "_class": "shapeGroup", "color": [1, 1, 1, 1], "label": 1}, {"id": "B0B2035B-C1A0-42D3-B8C1-E8E0C1A5CD1C", "name": "Stroke 247", "rect": {"x": 298.49997837430146, "y": 391.926336375489, "width": 15.000043435814405, "height": 14.990873533246486}, "_class": "shapeGroup", "color": [0.0, 0.0, 0.0, 0.0], "label": 1}, {"id": "EC6E8DE3-7F43-4B38-88FF-CF65F6AAD98C", "name": "Stroke 248", "rect": {"x": 303.5, "y": 396.9230769230769, "width": 5, "height": 4.997392438070392}, "_class": "shapeGroup", "color": [0.0, 0.0, 0.0, 0.0], "label": 1}, {"id": "D41542A5-30B4-43E6-96F2-FD2EA764889F", "name": "Settings", "rect": {"x": 268, "y": 421, "width": 77, "height": 18}, "_class": "text", "color": [0.847, 0.847, 0.847, 1], "label": 1}, {"id": "39BEB308-58F4-4E01-85C7-A650830772D8", "name": "Base", "rect": {"x": -31, "y": 297, "width": 198, "height": 231}, "_class": "shapeGroup", "color": [1, 1, 1, 1], "label": 1}, {"id": "B92C3458-E7D5-4EC9-A7FE-EAB8B095D362", "name": "Messages", "rect": {"x": 38, "y": 421, "width": 60, "height": 18}, "_class": "text", "color": [0.847, 0.847, 0.847, 1], "label": 1}, {"id": "6CF7FF17-B40A-4912-9EFA-E595B3D4BC6E", "name": "Base", "rect": {"x": 134, "y": 339, "width": 110, "height": 143}, "_class": "shapeGroup", "color": [1, 1, 1, 1], "label": 1}, {"id": "4AD49DED-E035-4CE5-9938-9D1D8FD11F40", "name": "Shop", "rect": {"x": 168, "y": 421, "width": 42, "height": 18}, "_class": "text", "color": [0.847, 0.847, 0.847, 1], "label": 1}, {"id": "D6D4A088-777D-468F-9443-10FA68E48880", "name": "Stroke 128", "rect": {"x": 181.5, "y": 397.2359843546284, "width": 15, "height": 9.994132985658439}, "_class": "shapeGroup", "color": [0.0, 0.0, 0.0, 0.0], "label": 1}, {"id": "817C763F-0F17-4E13-BD53-6885F460E450", "name": "Stroke 129", "rect": {"x": 184.4999816896734, "y": 392.23924380704045, "width": 9.00003662065319, "height": 5.996758857914358}, "_class": "shapeGroup", "color": [0.0, 0.0, 0.0, 0.0], "label": 1}, {"id": "2665EAC8-4E1E-45DF-8096-1D9F092CA321", "name": "Stroke 130", "rect": {"x": 186.5, "y": 400.2340286831811, "width": 1, "height": 3.998044328552794}, "_class": "shapeGroup", "color": [0.0, 0.0, 0.0, 0.0], "label": 1}, {"id": "AE2C7223-CA00-40A7-BD23-BE93A2C13FDE", "name": "Stroke 131", "rect": {"x": 190.5, "y": 400.2340286831811, "width": 1, "height": 3.998044328552794}, "_class": "shapeGroup", "color": [0.0, 0.0, 0.0, 0.0], "label": 1}, {"id": "0539C67F-BF48-4461-A006-21924E2A6312", "name": "Base", "rect": {"x": 90, "y": 164, "width": 198, "height": 231}, "_class": "shapeGroup", "color": [0.9921568627450981, 0.5843137254901961, 0.7333333333333332, 1], "label": 1}, {"id": "098403A5-FB28-45C6-B609-9F932687A890", "name": "Stroke 203", "rect": {"x": 185.5, "y": 239.5, "width": 7, "height": 1}, "_class": "shapeGroup", "color": [0.0, 0.0, 0.0, 0.0], "label": 1}, {"id": "12593EF1-EC97-4434-ACA4-61EA9787771F", "name": "Stroke 204", "rect": {"x": 185.5, "y": 242.5, "width": 7, "height": 1}, "_class": "shapeGroup", "color": [0.0, 0.0, 0.0, 0.0], "label": 1}, {"id": "9C0BB683-FE3C-4A8F-AEBC-171536181D56", "name": "Stroke 205", "rect": {"x": 182.5, "y": 232.5, "width": 13, "height": 15}, "_class": "shapeGroup", "color": [0.0, 0.0, 0.0, 0.0], "label": 1}, {"id": "B5EACE22-8832-435D-BD97-39336383D6BD", "name": "Stroke 206", "rect": {"x": 185.5, "y": 236.5, "width": 5, "height": 1}, "_class": "shapeGroup", "color": [0.0, 0.0, 0.0, 0.0], "label": 1}, {"id": "5E72AFF5-A0D9-4F9E-8AEB-F5F2F0795B57", "name": "News", "rect": {"x": 169, "y": 268, "width": 42, "height": 18}, "_class": "text", "color": [0.847, 0.847, 0.847, 1], "label": 1}, {"id": "760E0ABA-9391-4C0D-B800-0E4E768F3592", "name": "Stroke 212", "rect": {"x": 60.5, "y": 392.0306388526727, "width": 15, "height": 14.991780988649737}, "_class": "shapeGroup", "color": [0.0, 0.0, 0.0, 0.0], "label": 1}, {"id": "D3C69CA8-0C46-4C9A-BCC0-7221F0081EBF", "name": "Stroke 213", "rect": {"x": 64.5, "y": 395.5, "width": 7, "height": 1}, "_class": "shapeGroup", "color": [0.0, 0.0, 0.0, 0.0], "label": 1}, {"id": "16F269B8-2957-4A3E-9E83-54214CFB1CEF", "name": "Stroke 214", "rect": {"x": 64.5, "y": 398.5, "width": 5, "height": 1}, "_class": "shapeGroup", "color": [0.0, 0.0, 0.0, 0.0], "label": 1}, {"id": "E8F4138F-FEC1-4C05-9ACD-7BA4E108E0F3", "name": "Log Out", "rect": {"x": 149, "y": 593, "width": 77, "height": 18}, "_class": "text", "color": [0.847, 0.847, 0.847, 1], "label": 1}, {"id": "28AB6A92-2C0E-4589-B80F-55A333AE1CF5", "name": "Olga Weaver", "rect": {"x": 101, "y": 26, "width": 92, "height": 60}, "_class": "text", "color": [0.847, 0.847, 0.847, 1], "label": 1}, {"id": "9D520C75-301A-48D2-B928-7095EFAC627A", "name": "Stroke 112", "rect": {"x": 324.78374569219477, "y": 64.52666697008553, "width": 12.869753388517893, "height": 12.869753388517736}, "_class": "shapeGroup", "color": [0.0, 0.0, 0.0, 0.0], "label": 1}, {"id": "44222BBB-D8E0-40A6-A44F-653BB9D758A8", "name": "Stroke 113", "rect": {"x": 324.3533417762301, "y": 64.52666697008553, "width": 12.862912531575148, "height": 12.862912531575205}, "_class": "shapeGroup", "color": [0.0, 0.0, 0.0, 0.0], "label": 1}, {"id": "1CB7FF87-5877-4DFE-9E01-E17DECE81DAE", "name": "Avatar", "rect": {"x": -22, "y": 41, "width": 150, "height": 152}, "_class": "shapeGroup", "color": [0.9176232993197279, 0.9176232993197279, 0.9176232993197279, 1], "label": 1}, {"id": "09F09653-DD6F-4707-B400-90C0E207290B", "name": "Combined Shape", "rect": {"x": 4, "y": 48, "width": 139, "height": 139}, "_class": "shapeGroup", "color": [0.592156862745098, 0.8745098039215686, 0.9176470588235294, 1], "label": 1}, {"id": "D84E7C54-CDF3-461D-8320-12E7F408BA7B", "name": "Stroke 112", "rect": {"x": 70.40000003576279, "y": 101.8166667024293, "width": 6.243478189343932, "height": 1.1999999284744263}, "_class": "shapeGroup", "color": [0.0, 0.0, 0.0, 0.0], "label": 1}, {"id": "9F48FA70-24B9-4772-B124-84FCF3EDB007", "name": "Stroke 113", "rect": {"x": 72.8166667024293, "y": 99.40000003576279, "width": 1.1999999284744263, "height": 6.240190393867536}, "_class": "shapeGroup", "color": [0.0, 0.0, 0.0, 0.0], "label": 1}], "width": 375, "height": 667, "layer_width": 64, "layer_height": 64}